Workbook

Sheet Дог.
A4: ='Пр №1'!B20 -> XXXXXXX | D4: ='Пр №1'!J20 -> 46031.872 | F4: ='Пр №1'!L20 -> 46031.872 | H4: ='Пр №1'!P30 -> 3000
D5: ='Пр №1'!J21 -> 46031 | F5: ='Пр №1'!L21 -> 46032
B7: Телефон: | D7: ХХХХ ХХХ ХХХХХ | K7: Телефон: | M7: +996 (552) 727 607
G8: Филиал № | J8: 1 | L8: ул. Лермонтова д.№ 68
A9: Договор аренды оборудования (имущественного найма)
I10: № | J10: =J13 -> 9 | K10: =MONTH(L13&11) -> 1 | L10: =N13 -> 2026 | M10: =D4 -> 46031.872 | N10: =J8 -> 1 | P10: 46023
P11: =+TODAY() -> 46031
A12: XXXXXXX
B13: г. Бишкек | I13: « | J13: =DAY(TODAY()) -> 9 | K13: » | L13: =TEXT(P11,"ММММ") -> Январь | N13: =YEAR(TODAY()) -> 2026 | O13: г.
A14: Зинченко Михаил Александрович | G14: 22.12.2006 года рождения, паспорт: ID3219844 выдан MKK 218011 от 12.02.2023 г.
A15: зарегистрированный по адресу город Бишкек, улица Ялтинская 56/1, действующий на основании Свидетельства о государственной
A16: регистрации индивидуального предпринимателя по Свердловскому району г. Бишкек № 003-2024-169-5930 от 08.08.2024
A17: ИНН: | C17: 22212200650516 | H17: именуемый в дальнейшем «Арендодатель», с одной стороны и
A18: ХХХХ ХХХХ ХХХХ | I18: именуемый(-ая) в дальнейшем «Арендатор», действующий(-ая)
A19: на основании паспорта: | E19: ХХХ | F19: № | G19: ХХХХХ | I19: выдан | J19: МКК | K19: ХХХХ | L19: от | M19: ХХХХ | N19: зарегистрированный(-ая)
A20: по адресу: | C20: Чуйская область г. Бишкек | J20: ул. ХХХХХ | N20: Факт. место проживания
A21: =C20 -> Чуйская область г. Бишкек | I21: =J20 -> ул. ХХХХХ
A22: ПИН: | C22: ХХХХ | G22: Адрес объекта:
A23: ХХХХХ | C23: года рождения | F23: с другой стороны заключили Договор о нижеследующем:
A24: 1. ПРЕДМЕТ ДОГОВОРА
A25: 1.1. Арендодатель обязуется передать во временное пользование инструменты, машины и другое оборудование для выполнения
A26: строительных работ, именуемое в дальнейшем «Имущество», а Арендатор в свою очередь обязуется оплатить арендную плату за
A27: пользование Имуществом Арендодателю, а также вернуть ему оборудование в порядке и сроки, указанные в Приложении №1
A28: к настоящему Договору.
A29: 1.2. Арендодатель и Арендатор определяют: наименование переданного Имущества, дату и время выдачи, дату и время возврата,
A30: стоимость арендной оплаты, сумму обеспечительного платежа и место возврата Имущества, в приложении №1 к договору.
A31: 1.3. Имущество, предоставляемое в аренду по настоящему Договору, должно использоваться по прямому назначению в
A32: соответствии с Правилами аренды строительного инструмента.
A33: 1.4. Арендатор ознакомлен, Арендодателем, с правилами эксплуатации и хранения Имущества, соблюдением правил техники
A34: безопасности.
A35: 2. ПРАВА И ОБЯЗАННОСТИ СТОРОН
... A60: питания, утраты защитных элементов, появления посторонних звуков в работе и других проявлений неисправности.
A61: , - в случае поломки имущества, известить по номеру | J61: =M7 -> +996 (552) 727 607 | M61: и сдать Имущество в течение 1-х суток с
A62: момента поломки в пункт выдачи для выяснения причин поломки;
A63: ,- эксплуатировать полученное Имущество в соответствии с правилами его эксплуатации и техническими
A64: характеристиками, соблюдая технику безопасности;
A67: =TRIM(SUBSTITUTE(LEFT(A14&" ",SEARCH(" ",A14&" ")+1)&"."& MID(A14&" ",SEARCH(" ",A14&" ",SEARCH(" ",A14&" ")+1),2)&"."," .",)) -> З. М. | D67: ____________________________ | K67: =TRIM(SUBSTITUTE(LEFT(A18&" ",SEARCH(" ",A18&" ")+1)&"."& MID(A18&" ",SEARCH(" ",A18&" ",SEARCH(" ",A18&" ")+1),2)&"."," .",)) -> ХХХХ Х. Х. | N67: _________________________
D68: (подпись) | N68: (подпись)
J70: ____________________________________________________
K71: (Расшифровка подписи)
A72: ,- следить за целостностью и сохранностью полученного в аренду Имущества;
A73: ,- самостоятельно не вскрывать и не ремонтировать переданное Имущество;
A74: ,- соблюдать технику безопасности при использовании Имущества;
A75: ,- по требованию Арендодателя предоставлять документ, удостоверяющий личность.
A76: , - не сдавать в субаренду Имущество, предоставленное Арендодателем по настоящему Договору;
A77: ,- не передавать свои права и обязанности по настоящему Договору, другому лицу, а также не вносить Имущество
A78: в уставной капитал в хозяйственные товарищества и общества или в качестве паевого взноса в иные кооперативы;
A79: 3. АРЕНДНАЯ ПЛАТА, ДЕНЕЖНЫЙ ЗАЛОГ
A80: 3.1. Стоимость услуг проката и обеспечительный платеж отражены в Приложении №1 к настоящему Договору.
A81: 3.2. За пользование Имуществом, предоставленным по настоящему Договору, Арендатор единовременно уплачивает сумму
A82: обеспечительного платежа в соответствии с Приложением №1 к настоящему договору. В случае увеличения сроков оговоренных
A83: в Приложении №1, составляется Акт расчета арендной платы за пользование Имуществом.
... A136: 8.5. Стоимость размещения информации на каждой площадке составляет 500 (пятьсот) сом.
A140: =TRIM(SUBSTITUTE(LEFT(A14&" ",SEARCH(" ",A14&" ")+1)&"."& MID(A14&" ",SEARCH(" ",A14&" ",SEARCH(" ",A14&" ")+1),2)&"."," .",)) -> З. М. | D140: ____________________________ | K140: =TRIM(SUBSTITUTE(LEFT(A18&" ",SEARCH(" ",A18&" ")+1)&"."& MID(A18&" ",SEARCH(" ",A18&" ",SEARCH(" ",A18&" ")+1),2)&"."," .",)) -> ХХХХ Х. Х. | N140: _________________________
D141: (подпись) | N141: (подпись)

Sheet Пр №1
A2: Приложение №1 к Договору аренды оборудования
I3: =Дог.!I10 -> № | J3: =Дог.!J10 -> 9 | K3: =Дог.!K10 -> 1 | L3: =Дог.!L10 -> 2026 | M3: =Дог.!M10 -> 46031.872 | N3: =Дог.!N10 -> 1
B5: г. Бишкек | I5: « | J5: =Дог.!J13 -> 9 | K5: » | L5: =Дог.!L13 -> Январь | N5: =Дог.!N13 -> 2026 | O5: г.
A6: =Дог.!A14 -> Зинченко Михаил Александрович | G6: =Дог.!G14 -> 22.12.2006 года рождения, паспорт: ID3219844 выдан MKK 218011 от 12.02.2023 г.
A7: =Дог.!A15 -> зарегистрированный по адресу город Бишкек, улица Ялтинская 56/1, действующий на основании Свидетельства о государственной
A8: =Дог.!A16 -> регистрации индивидуального предпринимателя по Свердловскому району г. Бишкек № 003-2024-169-5930 от 08.08.2024
A9: =Дог.!A17 -> ИНН: | C9: =Дог.!C17 -> 22212200650516 | H9: именуемый в дальнейшем «Арендодатель», с одной стороны и
A10: =Дог.!A18 -> ХХХХ ХХХХ ХХХХ | I10: именуемый(-ая) в дальнейшем «Арендатор», действующий(-ая)
A11: =Дог.!A19 -> на основании паспорта: | E11: =Дог.!E19 -> ХХХ | F11: =Дог.!F19 -> № | G11: =Дог.!G19 -> ХХХХХ | I11: =Дог.!I19 -> выдан | J11: =Дог.!J19 -> МКК | K11: =Дог.!K19 -> ХХХХ | L11: =Дог.!L19 -> от | M11: =Дог.!M19 -> ХХХХ | N11: =Дог.!N19 -> зарегистрированный(-ая)
A12: по адресу: | C12: =Дог.!C20 -> Чуйская область г. Бишкек | I12: =Дог.!J20 -> ул. ХХХХХ | N12: Факт. место проживания
A13: =Дог.!A21 -> Чуйская область г. Бишкек | H13: =Дог.!I21 -> ул. ХХХХХ
A14: ПИН: | C14: =Дог.!C22 -> ХХХХ | G14: Адрес объекта: | K14: =Дог.!K22 -> 0
A15: с другой стороны, а вместе именуемые «Стороны», составили настоящее приложение в соответствии с Договором
A16: аренды оборудования | E16: № | F16: =J3 -> 9 | G16: =K3 -> 1 | H16: =L3 -> 2026 | I16: =M3 -> 46031.872 | J16: =N3 -> 1 | K16: о нижеследующем:
A17: 1. В соответствии с пунктом 1.2. Договора аренды оборудования | K17: № | L17: =F16 -> 9 | M17: =G16 -> 1 | N17: =H16 -> 2026 | O17: =I16 -> 46031.872 | P17: =N3 -> 1 | Q17: Арендодатель
A18: передает Арендатору следующее имущество и вместе они определили (оговорили) стоимость арендной оплаты и сроки возврата Имущества:
A19: № | B19: Наименование Имущества | F19: Фактическая стоимость проката | G19: Дата и время фактического возврата Имущества | I19: Кол-во | J19: Дата и время выдачи Имущества | L19: Оговоренная дата и время возврата Имущества | N19: Стоимость аренды (найма) Имущества за 1 сутки | P19: Сумма обеспечительного платежа
A20: 1 | B20: =Дог.!A12 -> XXXXXXX | I20: 1 | J20: =NOW() -> 46031.872 | L20: =J20 -> 46031.872 | N20: 1500 | P20: 3000
J21: =DATE(L3,K3,J3) -> 46031 | L21: =J21+1 -> 46032
A22: 2 | J22: =IF(LEN(B22),J20,"") | L22: =J22
J23: =IF(LEN(B22),J21,"") | L23: =IF(LEN(B22),L21,"")
A24: 3 | J24: =IF(LEN(B24),J20,"") | L24: =J24
J25: =IF(LEN(B24),J21,"") | L25: =IF(LEN(B24),L21,"")
A26: 4 | J26: =IF(LEN(B26),J20,"") | L26: =J26
J27: =IF(LEN(B26),J21,"") | L27: =IF(LEN(B26),L21,"")
A28: 5 | J28: =IF(LEN(B28),J20,"") | L28: =J28
J29: =IF(LEN(B28),J21,"") | L29: =IF(LEN(B28),L21,"")
N30: Итого: | P30: =SUM(P20:Q29) -> 3000
A31: 2. Оговоренный срок возврата и арендной оплаты за пользование Имуществом | K31: =L20 -> 46031.872 | M31: =L21 -> 46032 | O31: В залоге | P31: паспорт
A32: 3. Арендатор обязуется оплатить арендную плату за пользование Имуществом, не позднее 5 (пяти) рабочих | O32: Предоплата
A33: дней с момента возврата Имущества Арендодателю. (согласно пункту 3.6. договора аренды оборудования) | O33: Дата | Q33: Сумма
A34: =IF(LEN(P31),N34,"") -> 4. Арендатор добровольно передает личный паспорт гражданина в залог за арендуемое оборудование. | N34: 4. Арендатор добровольно передает личный паспорт гражданина в залог за арендуемое оборудование.
A35: 5. Исправность имущества, сдаваемого в аренду проверена Арендодателем в присутствии Арендатора.
A36: 6. Имущество передается Арендатору и возвращается по месту нахождения пункта проката Арендодателя
D37: Пункт проката : | H37: =Дог.!L8 -> ул. Лермонтова д.№ 68
A38: Арендная оплата и обеспечительный платеж .
A39: 1. Обеспечительный платеж взимается на момент заключения настоящего приложения, путем передачи наличными денежных средств,
A40: Арендатором Арендодателю или путем перечисления суммы на расчетный счет Арендодателя.
A41: 2. В случае досрочного возврата имущества Арендатору возвращается сумма за неиспользованное время проката Имущества.
A42: 3. Арендатор предоставляет Арендодателю обеспечительный платеж в размере | M42: =P30 -> 3000 | O42: При этом в случае
A43: ненадлежащего выполнения Арендатором своих обязательств по настоящему Договору, Арендодатель вправе вычесть из суммы обеспечительного
A44: платежа определенную сумму на покрытие реально нанесённого ущерба.
A45: 4. При надлежащим исполнении Арендатором своих обязательств по настоящему Договору, сумма обеспечительного платежа возвращается
A46: Арендатору в момент возврата Имущества Арендодателю.
A47: 5. Настоящее Приложение составлено в 2-ух экземплярах, имеющих одинаковую юридическую силу, по одному для каждой из сторон.
A48: 8. РЕКВИЗИТЫ СТОРОН
A49: АРЕНДОДАТЕЛЬ: | J49: АРЕНДАТОР:
A50: Ф.И.О.: | B50: =Дог.!A14 -> Зинченко Михаил Александрович | J50: =A50 -> Ф.И.О.: | L50: =A10 -> ХХХХ ХХХХ ХХХХ
A51: ИНН: | B51: =Дог.!C17 -> 22212200650516 | J51: ПИН: | L51: =C14 -> ХХХХ
A52: Паспорт: | C52: ID | D52: № | E52: 3219844 | J52: =A52 -> Паспорт: | L52: =E11 -> ХХХ | M52: =F11 -> № | N52: =G11 -> ХХХХХ
A53: Выдан: | C53: МКК 218011 от 12.02.2023 | J53: =A53 -> Выдан: | L53: =J11 -> МКК | M53: =K11 -> ХХХХ | N53: =L11 -> от | O53: =M11 -> ХХХХ
A54: Адрес: | C54: г. Бишкек | J54: =A54 -> Адрес: | L54: =C12 -> Чуйская область г. Бишкек
A55: ул. Ялтинская д. № 56 | J55: =I12 -> ул. ХХХХХ
A56: Почтовый индекс: | D56: 720051 | J56: =A56 -> Почтовый индекс:
A57: Банковские реквизиты: | J57: =A57 -> Банковские реквизиты:
A58: ОАО "МБАНК" ФИЛИАЛ "МБАНК ПЛАЗА"
A59: р/c: | B59: "1033220001521202" | J59: =A59 -> р/c:
A60: БИК: | B60: 103032 | J60: =A60 -> БИК:
A61: УГНС 003 Свердловского района | J61: УГНС 000
A62: ОКПО: | B62: 33158934
A63: =TRIM(SUBSTITUTE(LEFT(A6&" ",SEARCH(" ",A6&" ")+1)&"."& MID(A6&" ",SEARCH(" ",A6&" ",SEARCH(" ",A6&" ")+1),2)&"."," .",)) -> З. М. | D63: ________________________ | J63: =TRIM(SUBSTITUTE(LEFT(A10&" ",SEARCH(" ",A10&" ")+1)&"."& MID(A10&" ",SEARCH(" ",A10&" ",SEARCH(" ",A10&" ")+1),2)&"."," .",)) -> ХХХХ Х. Х. | M63: ________________________
D64: (подпись) | M64: =Дог.!M126 -> 0
A65: « | B65: =Дог.!J13 -> 9 | C65: » | D65: =Дог.!L13 -> Январь | F65: =Дог.!N13 -> 2026 | G65: г. | J65: =A65 -> « | K65: =B65 -> 9 | L65: =C65 -> » | M65: =D65 -> Январь | O65: =F65 -> 2026 | P65: =G65 -> г.
A66: Телефон: | C66: =Дог.!J61 -> +996 (552) 727 607 | J66: Телефон: | L66: =Дог.!D7 -> ХХХХ ХХХ ХХХХХ

Sheet Акт прием
A3: АКТ ПРИЕМА-ПЕРЕДАЧИ ИМУЩЕСТВА В ПРОКАТ
A4: к Договору аренды оборудования
J5: № | K5: ='Пр №1'!J3 -> 9 | L5: ='Пр №1'!K3 -> 1 | M5: ='Пр №1'!L3 -> 2026 | N5: ='Пр №1'!M3 -> 46031.872 | O5: ='Пр №1'!N3 -> 1
B6: =Дог.!B13 -> г. Бишкек | I6: ='Пр №1'!I5 -> « | J6: ='Пр №1'!J5 -> 9 | K6: ='Пр №1'!K5 -> » | L6: ='Пр №1'!L5 -> Январь | N6: ='Пр №1'!N5 -> 2026 | O6: ='Пр №1'!O5 -> г.
A7: ='Пр №1'!A6:E6 -> Зинченко Михаил Александрович | G7: ='Пр №1'!G6:Q6 -> 22.12.2006 года рождения, паспорт: ID3219844 выдан MKK 218011 от 12.02.2023 г.
A8: ='Пр №1'!A7:Q7 -> зарегистрированный по адресу город Бишкек, улица Ялтинская 56/1, действующий на основании Свидетельства о государственной
A9: ='Пр №1'!A8:Q8 -> регистрации индивидуального предпринимателя по Свердловскому району г. Бишкек № 003-2024-169-5930 от 08.08.2024
A10: ='Пр №1'!A9:G9 -> ИНН: | C10: ='Пр №1'!C9:G9 -> 22212200650516 | H10: именуемый в дальнейшем «Арендодатель», с одной стороны и
A11: =Дог.!A18 -> ХХХХ ХХХХ ХХХХ | I11: именуемый(-ая) в дальнейшем «Арендатор», действующий(-ая)
A12: =Дог.!A19 -> на основании паспорта: | E12: =Дог.!E19 -> ХХХ | F12: =Дог.!F19 -> № | G12: =Дог.!G19 -> ХХХХХ | I12: =Дог.!I19 -> выдан | J12: =Дог.!J19 -> МКК | K12: ='Пр №1'!K11 -> ХХХХ | L12: ='Пр №1'!L11 -> от | M12: ='Пр №1'!M11 -> ХХХХ | N12: =Дог.!N19 -> зарегистрированный(-ая)
A13: по адресу: | C13: ='Пр №1'!C12:G12 -> Чуйская область г. Бишкек | I13: ='Пр №1'!I12:M12 -> ул. ХХХХХ | N13: Факт. место проживания
A14: ='Пр №1'!A13:E13 -> Чуйская область г. Бишкек | H14: ='Пр №1'!H13:Q13 -> ул. ХХХХХ
A15: ПИН: | C15: ='Пр №1'!C14:F14 -> ХХХХ | G15: Адрес объекта: | K15: ='Пр №1'!K14:P14 -> 0
A16: с другой стороны, а вместе именуемые «Стороны», заключили настоящий акт к Договору
A17: аренды оборудования | E17: № | F17: =K5 -> 9 | G17: =L5 -> 1 | H17: =M5 -> 2026 | I17: =N5 -> 46031.872 | J17: =O5 -> 1 | K17: о нижеследующем:
A18: 1. Во исполнение Договора аренды оборудования | J18: № | K18: =K5 -> 9 | L18: =L5 -> 1 | M18: =M5 -> 2026 | N18: =N5 -> 46031.872 | O18: =O5 -> 1
A19: Арендодатель передал Арендатору следующее Имущество:
A20: № | B20: Наименование Имущества | J20: Кол-Во | L20: Завод. или индеф. № | N20: Стоимость оборудования
A21: ='Пр №1'!A20 -> 1 | B21: ='Пр №1'!B20 -> XXXXXXX | J21: ='Пр №1'!I20 -> 1 | L21: 112 | N21: =35000*J21 -> 35000
A22: 2 | B22: ='Пр №1'!B22 -> 0 | J22: ='Пр №1'!I22 -> 0
A23: 3 | B23: ='Пр №1'!B24 -> 0 | J23: ='Пр №1'!I24 -> 0
A24: 4 | B24: ='Пр №1'!B26 -> 0 | J24: ='Пр №1'!I26 -> 0
A25: 5 | B25: ='Пр №1'!B28 -> 0 | J25: ='Пр №1'!I28 -> 0
A26: Итого: стоимость оборудования | N26: =SUM(N21:Q25) -> 35000
A27: 2. Имущество передается в полной исправности. Работоспособность Имущества проверена в присутствии Арендатора
A28: 3. Арендодатель ознакомил Арендатора с правилами эксплуатации и хранения Имущества, с правилами техники безопасности.
A29: 4. Настоящим Арендодатель подтверждает получение от Арендатора суммы обеспечительного платежа в размере | O29: ='Пр №1'!P30 -> 3000
A30: 5. Настоящий Акт составлен в 2-ух экземплярах, имеющих одинаковую юридическую силу, по одному для каждой из сторон.
A33: 8. РЕКВИЗИТЫ СТОРОН
A34: АРЕНДОДАТЕЛЬ: | J34: АРЕНДАТОР:
A35: Ф.И.О.: | B35: ='Пр №1'!B50:G50 -> Зинченко Михаил Александрович | J35: ='Пр №1'!J50:K50 -> Ф.И.О.: | L35: ='Пр №1'!L50:Q50 -> ХХХХ ХХХХ ХХХХ
A36: ИНН: | B36: ='Пр №1'!B51:G51 -> 22212200650516 | J36: ='Пр №1'!J51:K51 -> ПИН: | L36: ='Пр №1'!L51:P51 -> ХХХХ
A37: Паспорт: | C37: ='Пр №1'!C52 -> ID | D37: № | E37: ='Пр №1'!E52:G52 -> 3219844 | J37: ='Пр №1'!J52:K52 -> Паспорт: | L37: ='Пр №1'!L52 -> ХХХ | M37: № | N37: ='Пр №1'!N52:O52 -> ХХХХХ
A38: Выдан: | C38: ='Пр №1'!C53:G53 -> МКК 218011 от 12.02.2023 | J38: ='Пр №1'!J53:K53 -> Выдан: | L38: ='Пр №1'!L53 -> МКК | M38: ='Пр №1'!M53 -> ХХХХ | N38: ='Пр №1'!N53 -> от | O38: ='Пр №1'!O53 -> ХХХХ
A39: Адрес: | C39: ='Пр №1'!C54:G54 -> г. Бишкек | J39: ='Пр №1'!J54:K54 -> Адрес: | L39: ='Пр №1'!L54:Q54 -> Чуйская область г. Бишкек
A40: ='Пр №1'!A55:G55 -> ул. Ялтинская д. № 56 | J40: ='Пр №1'!J55:P55 -> ул. ХХХХХ
A41: Почтовый индекс: | D41: ='Пр №1'!D56:G56 -> 720051 | J41: ='Пр №1'!J56:L56 -> Почтовый индекс: | M41: ='Пр №1'!M56:N56 -> 0
A42: Банковские реквизиты: | J42: ='Пр №1'!J57:P57 -> Банковские реквизиты:
A43: ='Пр №1'!A58:G58 -> ОАО "МБАНК" ФИЛИАЛ "МБАНК ПЛАЗА" | J43: ='Пр №1'!J58:P58 -> 0
A44: р/c: | B44: ='Пр №1'!B59:G59 -> "1033220001521202" | J44: ='Пр №1'!J59 -> р/c: | K44: ='Пр №1'!K59:P59 -> 0
A45: БИК: | B45: ='Пр №1'!B60:G60 -> 103032 | J45: ='Пр №1'!J60 -> БИК: | K45: ='Пр №1'!K60:P60 -> 0
A46: ='Пр №1'!A61:G61 -> УГНС 003 Свердловского района | J46: ='Пр №1'!J61:P61 -> УГНС 000
A47: ='Пр №1'!A62 -> ОКПО: | B47: ='Пр №1'!B62 -> 33158934
A48: ='Пр №1'!A63:C63 -> З. М. | D48: ='Пр №1'!D63:F63 -> ________________________ | J48: ='Пр №1'!J63:L63 -> ХХХХ Х. Х. | M48: ________________________
D49: ='Пр №1'!D64:F64 -> (подпись) | M49: ='Пр №1'!M64:P64 -> 0
A50: ='Пр №1'!A65 -> « | B50: ='Пр №1'!B65 -> 9 | C50: ='Пр №1'!C65 -> » | D50: ='Пр №1'!D65:E65 -> Январь | F50: ='Пр №1'!F65 -> 2026 | G50: ='Пр №1'!G65 -> г. | J50: =A50 -> « | K50: =B50 -> 9 | L50: =C50 -> » | M50: =D50 -> Январь | O50: =F50 -> 2026 | P50: =G50 -> г.
A51: Телефон: | C51: ='Пр №1'!C66:G66 -> +996 (552) 727 607 | J51: Телефон: | L51: ='Пр №1'!L66:P66 -> ХХХХ ХХХ ХХХХХ

Sheet Акт расч
A3: АКТ РАСЧЕТА АРЕНДНОЙ ПЛАТЫ
A4: к Договору аренды оборудования
J5: № | K5: ='Пр №1'!J3 -> 9 | L5: ='Пр №1'!K3 -> 1 | M5: ='Пр №1'!L3 -> 2026 | N5: ='Пр №1'!M3 -> 46031.872 | O5: ='Акт прием'!O5 -> 1
B6: =Дог.!B13 -> г. Бишкек | I6: ='Пр №1'!I5 -> « | J6: ='Пр №1'!J5 -> 9 | K6: ='Пр №1'!K5 -> » | L6: ='Пр №1'!L5 -> Январь | N6: ='Пр №1'!N5 -> 2026 | O6: ='Пр №1'!O5 -> г.
A7: ='Акт прием'!A7:E7 -> Зинченко Михаил Александрович | G7: ='Акт прием'!G7:Q7 -> 22.12.2006 года рождения, паспорт: ID3219844 выдан MKK 218011 от 12.02.2023 г.
A8: ='Пр №1'!A7:Q7 -> зарегистрированный по адресу город Бишкек, улица Ялтинская 56/1, действующий на основании Свидетельства о государственной
A9: ='Пр №1'!A8:Q8 -> регистрации индивидуального предпринимателя по Свердловскому району г. Бишкек № 003-2024-169-5930 от 08.08.2024
A10: ='Акт прием'!A10:G10 -> ИНН: | C10: ='Пр №1'!C9:G9 -> 22212200650516 | H10: именуемый в дальнейшем «Арендодатель», с одной стороны и
A11: =Дог.!A18 -> ХХХХ ХХХХ ХХХХ | I11: именуемый(-ая) в дальнейшем «Арендатор», действующий(-ая)
A12: =Дог.!A19 -> на основании паспорта: | E12: =Дог.!E19 -> ХХХ | F12: =Дог.!F19 -> № | G12: =Дог.!G19 -> ХХХХХ | I12: =Дог.!I19 -> выдан | J12: =Дог.!J19 -> МКК | K12: ='Пр №1'!K11 -> ХХХХ | L12: ='Пр №1'!L11 -> от | M12: ='Пр №1'!M11 -> ХХХХ | N12: =Дог.!N19 -> зарегистрированный(-ая)
A13: по адресу: | C13: ='Акт прием'!C13:G13 -> Чуйская область г. Бишкек | I13: ='Акт прием'!I13:M13 -> ул. ХХХХХ | N13: Факт. место проживания
A14: ='Акт прием'!A14:E14 -> Чуйская область г. Бишкек | H14: ='Пр №1'!H13:Q13 -> ул. ХХХХХ
A15: ПИН: | C15: ='Пр №1'!C14:F14 -> ХХХХ | G15: Адрес объекта: | K15: ='Пр №1'!K14:P14 -> 0
A16: с другой стороны, а вместе именуемые «Стороны», заключили настоящий акт к Договору аренды оборудования о нижеследующем:
A17: 1. Во исполнение Договора аренды оборудования | J17: № | K17: =K5 -> 9 | L17: =L5 -> 1 | M17: =M5 -> 2026 | N17: =N5 -> 46031.872 | O17: =O5 -> 1
A18: Арендатор возвращает, а Арендодатель принимает следующее Имущество и рассчитывает арендную плату за пользование оборудованием:
A19: № | B19: Наименование Имущества | F19: ='Пр №1'!J19 -> Дата и время выдачи Имущества | G19: ='Акт возв'!J20 -> Дата и время возврата | H19: Расчетный период аренды | J19: Количество оборудования | L19: Кол. Суток | M19: Ед.Изм. | N19: Цена в сутки | P19: Сумма сом
A20: 1 | B20: ='Пр №1'!B20 -> XXXXXXX | F20: ='Пр №1'!J20 -> 46031.872 | H20: ='Пр №1'!J20 -> 46031.872 | J20: ='Пр №1'!I20 -> 1 | L20: =H21-F21 -> 0 | M20: Сут | N20: ='Пр №1'!N20 -> 1500 | P20: =J20*L20*N20 -> 0
F21: ='Пр №1'!J21 -> 46031 | H21: ='Пр №1'!J21 -> 46031
A22: 2 | B22: ='Пр №1'!B22:E23 -> 0 | J22: ='Пр №1'!I22 -> 0 | L22: =H23-F23 -> 0 | P22: =J22*L22*N22 -> 0
A24: 3 | B24: ='Пр №1'!B24:E25 -> 0 | J24: ='Пр №1'!I24 -> 0 | L24: =H25-F25 -> 0 | P24: =J24*L24*N24 -> 0
A26: 4 | B26: ='Пр №1'!B26:E27 -> 0 | J26: ='Пр №1'!I26 -> 0 | L26: =H27-F27 -> 0 | P26: =J26*L26*N26 -> 0
A28: 5 | B28: ='Пр №1'!B28:E29 -> 0 | J28: ='Пр №1'!I28 -> 0 | L28: =H29-F29 -> 0 | P28: =J28*L28*N28 -> 0
A30: 6 | L30: =H31-F31 -> 0 | P30: =J30*L30*N30 -> 0
A32: 7 | L32: =H33-F33 -> 0 | P32: =J32*L32*N32 -> 0
A34: 8 | L34: =H35-F35 -> 0 | P34: =J34*L34*N34 -> 0
A36: 9 | L36: =H37-F37 -> 0 | P36: =J36*L36*N36 -> 0
A38: 10 | L38: =H39-F39 -> 0 | P38: =J38*L38*N38 -> 0
B40: Скидка | P40: =(SUM(P20:Q39))*N40 -> 0
J41: Дата Сегодня: | M41: ='Пр №1'!J21 -> 46031 | N41: Всего: | P41: =SUM(P20:Q39) -> 0
J42: Дата Обязательство: | M42: =Обяз!K22 -> 46032 | N42: Депозит: | P42: ='Пр №1'!P30:Q30 -> 3000
A43: № | B43: Расчет неустоек | L43: Ед. Изм. | N43: Кол. Суток
A44: 1 | B44: Количество суток просрочки невозврата Имущества | L44: Сегодня: | N44: ='Пр №1'!J21 -> 46031
A45: 2 | B45: Согласно пункту 2.8. Неустойка 1% за каждые сутки просрочки не возврата Имущества | L45: Сутки | P45: ='Акт прием'!N21*1%*N45 -> 0
A46: 3 | B46: Количество суток просрочки арендного платежа | L46: Обязательство: | N46: =M42 -> 46032
A47: 4 | B47: Согласно пункту 3.6. Неустойка 1% за каждые сутки просрочки арендного платежа | L47: Сутки | P47: ='Акт прием'!N21*1%*N47 -> 0
A48: 5 | B48: Неустойка по ОБЯЗАТЕЛЬСТВУ 1 (один) % от оставшейся суммы общего долга в день | L48: Сумма долга | P48: =(P41-P42)*1%*N48 -> 0
B49: Итого к оплате: | P49: =P41-P42+P45+P47+P48-P40 -> -3000
A50: 2. Имущество передается в полной исправности. Работоспособность Имущества проверена Арендодателем
A51: 3. Настоящим Арендодатель подтверждает получение предоплаты в размере | M51: =P42 -> 3000 | P51: от Арендатора.
A52: 4. Арендатор обязуется оплатить образовавшуюся задолженность в размере | J52: =P49 -> -3000 | M52: не позднее 5 (пяти) рабочих дней с момента
A53: подписания данного Акта.
A54: 5. Согласно пункту 3.6. договора аренды оборудования: В случае просрочки арендного платежа в установленный договором срок (5 (пять)
A55: рабочих дней), Арендатор оплачивает неустойку, в размере 1 (один) % от стоимости оборудования, за каждые сутки просрочки
A56: (стоимость оборудования указана в акте приема передачи)
A57: 6. Настоящий Акт составлен в 2-ух экземплярах, имеющих одинаковую юридическую силу, по одному для каждой из сторон.
A58: 8. РЕКВИЗИТЫ СТОРОН
A59: АРЕНДОДАТЕЛЬ: | J59: АРЕНДАТОР:
A60: Ф.И.О.: | B60: ='Пр №1'!B50:G50 -> Зинченко Михаил Александрович | J60: ='Акт прием'!J35:K35 -> Ф.И.О.: | L60: ='Пр №1'!L50:Q50 -> ХХХХ ХХХХ ХХХХ
A61: ИНН: | B61: ='Пр №1'!B51:G51 -> 22212200650516 | J61: ='Акт прием'!J36:K36 -> ПИН: | L61: ='Пр №1'!L51:P51 -> ХХХХ
A62: Паспорт: | C62: ='Пр №1'!C52 -> ID | D62: № | E62: ='Пр №1'!E52:G52 -> 3219844 | J62: ='Акт прием'!J37:K37 -> Паспорт: | L62: ='Пр №1'!L52 -> ХХХ | M62: № | N62: ='Пр №1'!N52:O52 -> ХХХХХ
A63: Выдан: | C63: ='Пр №1'!C53:G53 -> МКК 218011 от 12.02.2023 | J63: ='Акт прием'!J38:K38 -> Выдан: | L63: ='Пр №1'!L53 -> МКК | M63: ='Пр №1'!M53 -> ХХХХ | N63: ='Пр №1'!N53 -> от | O63: ='Пр №1'!O53 -> ХХХХ
A64: Адрес: | C64: ='Пр №1'!C54:G54 -> г. Бишкек | J64: ='Акт прием'!J39:K39 -> Адрес: | L64: ='Пр №1'!L54:Q54 -> Чуйская область г. Бишкек
A65: ='Пр №1'!A55:G55 -> ул. Ялтинская д. № 56 | J65: ='Пр №1'!J55:P55 -> ул. ХХХХХ
A66: Почтовый индекс: | D66: ='Пр №1'!D56:G56 -> 720051 | J66: ='Акт прием'!J41:L41 -> Почтовый индекс: | M66: ='Пр №1'!M56:N56 -> 0
A67: Банковские реквизиты: | J67: ='Акт прием'!J42:P42 -> Банковские реквизиты:
A68: ='Пр №1'!A58:G58 -> ОАО "МБАНК" ФИЛИАЛ "МБАНК ПЛАЗА" | J68: ='Пр №1'!J58:P58 -> 0
A69: р/c: | B69: ='Пр №1'!B59:G59 -> "1033220001521202" | J69: ='Акт прием'!J44 -> р/c: | K69: ='Пр №1'!K59:P59 -> 0
A70: БИК: | B70: ='Пр №1'!B60:G60 -> 103032 | J70: ='Акт прием'!J45 -> БИК: | K70: ='Пр №1'!K60:P60 -> 0
A71: ='Пр №1'!A61:G61 -> УГНС 003 Свердловского района | J71: ='Пр №1'!J61:P61 -> УГНС 000
A72: ='Акт прием'!A47 -> ОКПО: | B72: ='Пр №1'!B62 -> 33158934
A73: ='Акт прием'!A48:C48 -> З. М. | D73: ='Акт прием'!D48:F48 -> ________________________ | J73: ='Пр №1'!J63:L63 -> ХХХХ Х. Х. | M73: ________________________
D74: ='Акт прием'!D49:F49 -> (подпись) | M74: ='Акт прием'!M49:P49 -> 0
A75: =A7 -> Зинченко Михаил Александрович | J75: Ф.И.О.
M76: (Расшифровка подписи)
A77: ='Пр №1'!A65 -> « | B77: ='Пр №1'!B65 -> 9 | C77: ='Пр №1'!C65 -> » | D77: ='Пр №1'!D65:E65 -> Январь | F77: ='Пр №1'!F65 -> 2026 | G77: ='Пр №1'!G65 -> г. | J77: =A77 -> « | K77: =B77 -> 9 | L77: =C77 -> » | M77: =D77 -> Январь | O77: =F77 -> 2026 | P77: =G77 -> г.
A78: Телефон: | C78: ='Пр №1'!C66:G66 -> +996 (552) 727 607 | J78: Телефон: | L78: ='Пр №1'!L66:P66 -> ХХХХ ХХХ ХХХХХ

Sheet Обяз
A2: =Дог.!B13 -> г. Бишкек | F2: =Дог.!I13 -> « | G2: =Дог.!J13 -> 9 | H2: =Дог.!K13 -> » | I2: =Дог.!L13 -> Январь | K2: =Дог.!N13 -> 2026 | L2: =Дог.!O13 -> г.
A6: ОБЯЗАТЕЛЬСТВО
B9: Я, | C9: =Дог.!A18 -> ХХХХ ХХХХ ХХХХ | J9: зарегистрированный (-ая)
A10: по адресу | C10: =Дог.!C20 -> Чуйская область г. Бишкек
A11: =Дог.!J20 -> ул. ХХХХХ | G11: Фактическое место проживание
A12: по адресу | C12: =Дог.!A21 -> Чуйская область г. Бишкек
A13: =Дог.!I21 -> ул. ХХХХХ
A14: Паспорт: | C14: =Дог.!E19 -> ХХХ | D14: № | E14: =Дог.!G19 -> ХХХХХ
A15: Выдан: | C15: =Дог.!J19 -> МКК | D15: =Дог.!K19 -> ХХХХ | E15: от | F15: =Дог.!M19 -> ХХХХ
A16: ПИН: | C16: =Дог.!C22 -> ХХХХ
A17: Год рождения | D17: =Дог.!A23 -> ХХХХХ
A18: Телефон | C18: =Дог.!D7 -> ХХХХ ХХХ ХХХХХ
A19: даю настоящее обязательство И.П. | F19: =Дог.!A14 -> Зинченко Михаил Александрович
A21: 1. | B21: Обязуюсь погасить задолженность в размере : | J21: ='Акт расч'!P49 -> -3000
A22: =[1]!ЧислоПрописьюВалюта(J21,2) -> #NAME? | J22: в срок до | K22: ='Пр №1'!J21+1 -> 46032
A23: Задолженность обязуюсь погашать равными долями по | J23: =J21/C24 -> -600
A24: в течении | C24: 5 | D24: месяцев\дней | F24: не позднее | H24: 5 | I24: ,-го рабочего дня каждого месяца
A25: Путем внесения наличных денег в кассу И.П. | G25: =Дог.!A14 -> Зинченко Михаил Александрович
A26: либо на мобильный кошелек Mega Pay по номеру | H26: =Дог.!M7 -> +996 (552) 727 607 | K26: с обязательным
A27: фотографированием чека оплаты задолженности и отправки его на WhatsApp этого же номера.
A28: 2. | B28: Предупрежден что, в случае просрочки выплат по обязательству, будет начисляться неустойка
A29: в соответствии со ст.320 ГК.КР., в размере 1 (один) % от оставшейся суммы общего долга за
A30: каждый день просрочки, от суммы основного долга. В рамках исполнения обязательства в
A31: случае просрочки, в первую очередь погашается неустойка.
A32: 3. | B32: Также предупрежден(а), что в случае неуплаты мною долга, дело о взыскании
A33: задолженности со всеми штрафными начислениями, будет передано в суд по месту нахождения
A34: кредитора г. Бишкек Свердловский районный суд (по адресу ул. Ибраимова д. № 64) в порядке
A35: установленном действующим законодательством КР.( договорная подсудность Ст.34 ГПК К.Р.)
A36: 4. | B36: В случае смены жительства и номеров телефонов обязуюсь в 3-х дневный срок
A37: сообщить новые данные.
A40: (Ф.И.О., должника) | J40: (подпись должника)
A43: (Ф.И.О., поручителя) | J43: (подпись поручителя)
A46: (Ф.И.О., поручителя) | J46: (подпись поручителя)
A48: =F19 -> Зинченко Михаил Александрович
A49: (Ф.И.О., кредитора) | J49: (подпись кредитора)

Sheet Пасп Доп Данные
A39: Акт дополнительных данных
K40: =Дог.!G8 -> Филиал № | M40: =Дог.!L8 -> ул. Лермонтова д.№ 68
M42: Дата: | N42: ='Пр №1'!J21 -> 46031
B43: г. Бишкек
A44: Арендодатель: | K44: Арендатор:
A45: ='Пр №1'!B50 -> Зинченко Михаил Александрович | K45: ='Пр №1'!L50 -> ХХХХ ХХХХ ХХХХ
A46: № | B46: Должник | C46: Паспортные данные | E46: Телефон | F46: Адрес | I46: Инструмент | J46: Кол-во суток | K46: Задолженность | L46: Примечание
A47: 1 | B47: ='Пр №1'!A10 -> ХХХХ ХХХХ ХХХХ | C47: =Дог.!E19 -> ХХХ | D47: =Дог.!G19 -> ХХХХХ | E47: =Дог.!D7 -> ХХХХ ХХХ ХХХХХ | F47: Рег. по паспорту | G47: =Дог.!C20 -> Чуйская область г. Бишкек | H47: =Дог.!J20 -> ул. ХХХХХ | I47: ='Пр №1'!B20 -> XXXXXXX | J47: ='Акт расч'!L20 -> 0 | K47: ='Акт расч'!P49 -> -3000
C48: =Дог.!J19 -> МКК | F48: Факт. место жительство | G48: =Дог.!A21 -> Чуйская область г. Бишкек | H48: =Дог.!I21 -> ул. ХХХХХ
C49: =Дог.!A22 -> ПИН: | D49: =Дог.!C22 -> ХХХХ
A50: № | B50: Родственники, друзья, знакомые. | C50: Паспортные данные | E50: Телефон | F50: Адрес | L50: Примечание
A51: 1 | B51: Жена
C53: =C49 -> ПИН:
A54: 2 | B54: Мать
C56: =C53 -> ПИН:
A57: 3 | B57: Любовница
C59: =C56 -> ПИН:
A60: 4
C62: =C59 -> ПИН:

Sheet Треб1
M1: 1
H2: =Дог.!A67 -> З. М.
J3: Контактный телефон
J4: =Дог.!M7 -> +996 (552) 727 607
J5: E-mail: alex.zin4@yandex.ru | O5: Взяли оборудование не оплатили арендную платы и не вернули оборудование
A9: УВЕДОМЛЕНИЕ АРЕНДАТОРУ
D11: Уважаемый (-ая) | F11: =Дог.!$A$18 -> ХХХХ ХХХХ ХХХХ | L11: =Дог.!A23 -> ХХХХХ | M11: г.р.
A13: Согласно договору аренды оборудования за № | G13: =Дог.!J10 -> 9 | H13: =Дог.!K10 -> 1 | I13: =Дог.!L10 -> 2026 | J13: =Дог.!M10 -> 46031.872 | K13: от | L13: ='Пр №1'!J21 -> 46031
A14: Вы взяли во временное пользование Имущество и обязались оплатить арендную плату за пользование и возвратить
A15: оборудование в порядке и сроки указанные в Приложении №1 настоящего договора аренды оборудования.
A16: Установленный договором срок возврата Имущества и оплаты арендной оплаты истек: | J16: =J13 -> 46031.872 | L16: ='Пр №1'!M31 -> 46032
A17: Вы не возвратили арендованное имущество в оговоренный срок и не оплатили стоимость арендной платы за пользование
A18: Имуществом.
A19: =H2 -> З. М. | C19: уведомляет что на | F19: ='Пр №1'!J21 -> 46031 | G19: у Вас имеется задолженность по арендной плате за пользование
A20: Имуществом в размере: | D20: ='Акт расч'!P49 -> -3000
A22: Прошу Вас до | C22: =F19+1 -> 46032 | E22: произвести оплату вашей задолженности и вернуть оборудование.
A24: А также напоминаю Вам, что заключённый между нами договор имущественного найма содержит следующие пункты:
A25: 2.5. Если Арендатор не возвратил арендованное имущество либо возвратил его несвоевременно, то Арендатор оплачивает
A26: арендную плату Арендодателю за пользование имуществом за все время просрочки (за все время нахождения имущества
A27: у Арендатора) в соответствии со ч 2. ст.561 ГК.К.Р. пункт 2
A28: 2.8. В случае невозвращения нанятого имущества в установленный договором срок, Арендатор оплачивает неустойку,
A29: в размере 1 (один) % от стоимости оборудования, за каждые сутки просрочки (стоимость оборудования указана в акте
A30: приема передачи) в соответствии со ч 2. ст.561 ГК.К.Р. пункт 2.
A31: 2.7. В случае задержки имущества более оговоренного срока, известить об этом Арендодателя за 1-и сутки и лично явится
A32: в пункт проката для продления договора аренды на новый срок.
A35: Ввиду вышеизложенного Вам необходимо произвести оплату образовавшейся задолженности и вернуть оборудование.
B40: Дата: | C40: =F19 -> 46031 | G40: =H2 -> З. М.
J41: (Подпись)
M45: 2
H46: =H2 -> З. М.
J47: Контактный телефон
J48: =J4 -> +996 (552) 727 607
J49: E-mail: alex.zin4@yandex.ru | O49: =O5 -> Взяли оборудование не оплатили арендную платы и не вернули оборудование
A53: ПРЕТЕНЗИЯ О ЗАДОЛЖНОСТИ
D55: Уважаемый (-ая) | F55: =Дог.!$A$18 -> ХХХХ ХХХХ ХХХХ | L55: =L11 -> ХХХХХ | M55: г.р.
A57: Согласно договору аренды оборудования за № | G57: =G13 -> 9 | H57: =H13 -> 1 | I57: =I13 -> 2026 | J57: =J13 -> 46031.872 | K57: от | L57: =L13 -> 46031
A58: Вы взяли во временное пользование Имущество и обязались оплатить арендную плату за пользование и возвратить
A59: оборудование в порядке и сроки указанные в Приложении №1 настоящего договора аренды оборудования.
A60: Установленный договором срок возврата Имущества и оплаты арендной оплаты истек: | J60: =J16 -> 46031.872 | L60: =L16 -> 46032
A61: Вы не возвратили арендованное имущество в оговоренный срок и не оплатили стоимость арендной платы за пользование
A62: Имуществом.
A63: =H46 -> З. М. | C63: уведомляет что на | F63: =F19 -> 46031 | G63: у Вас имеется задолженность по арендной плате за пользование
A64: Имуществом плюс неустойка, согласно пункту 2.8. Договора аренды оборудования и согласно ГРАЖДАНСКОМУ КОДЕКСУ
A65: КЫРГЫЗСКОЙ РЕСПУБЛИКИ Часть 2 статья 561 пункт 2. Неустойка в размере 1 (один) % от стоимости оборудования, за каждые
A66: сутки просрочки. | C66: Итого к оплате : | E66: ='Акт расч'!P49 -> -3000
A68: Прошу Вас до | C68: =F63+1 -> 46032 | E68: произвести оплату вашей задолженности и неустойки и вернуть оборудование.
A70: А также напоминаю Вам, что заключённый между нами договор имущественного найма содержит следующие пункты:
A71: 7.3. При подписании данного договора Арендатор дает согласие на хранение и обработку, своих персональных данных,
A72: получение информации, носящий рекламный характер, а также на публикацию ФИО, даты рождения, фотографий в сети
A73: Интернет и в черных списках на сайтах не надежных арендаторов, в случае возникновения долговых обязательств перед
A74: Арендодателем.
A75: В случае неуплаты до указанного срока вышеуказанной денежной суммы и невозврата оборудования в отношении Вас
A76: будут реализованы следующие действия:
A77: Согласно пункту 8.3. Договора аренды оборудования, Вы будете добавлены в общий черный список недобросовестных
A78: арендаторов по всему СНГ, а также Ваши данные будут размещены в аналогичных списках в социальных сетях в всемирной
A79: сети Интернет ("Одноклассники", "Фейсбук", "Инстаграм", "В контакте" и т. д.). Данные списки являются общедоступными,
A80: и любой человек вбивший Ваши данные в интернете сразу получит всю имеющуюся информацию о Вас, находящуюся
A81: на этих интернет ресурсах (сайтах) (Ваши фотографию, копию паспорта и т.д.)
... A84: Ввиду вышеизложенного прошу Вас незамедлительно принять решение по моей претензии!!!
B88: Дата: | C88: =F63 -> 46031 | G88: =G40 -> З. М.
J89: (Подпись)
M93: 3
H94: =H2 -> З. М.
J95: Контактный телефон
J96: =J48 -> +996 (552) 727 607
J97: E-mail: alex.zin4@yandex.ru | O97: =O49 -> Взяли оборудование не оплатили арендную платы и не вернули оборудование
A101: ДОСУДЕБНАЯ ПРЕТЕНЗИЯ
D103: Уважаемый (-ая) | F103: =Дог.!$A$18 -> ХХХХ ХХХХ ХХХХ | L103: =L55 -> ХХХХХ | M103: г.р.
A105: Согласно договору аренды оборудования за № | G105: =G57 -> 9 | H105: =H57 -> 1 | I105: =I57 -> 2026 | J105: =J57 -> 46031.872 | K105: от | L105: =L57 -> 46031
A106: Вы взяли во временное пользование Имущество и обязались оплатить арендную плату за пользование и возвратить
A107: оборудование в порядке и сроки указанные в Приложении №1 настоящего договора аренды оборудования.
A108: Установленный договором срок возврата Имущества и оплаты арендной оплаты истек: | J108: =J60 -> 46031.872 | L108: =L60 -> 46032
A109: Вы не возвратили арендованное имущество в оговоренный срок и не оплатили стоимость арендной платы за пользование
A110: Имуществом.
A111: =H94 -> З. М. | C111: уведомляет что на | F111: =F63 -> 46031 | G111: у Вас имеется просроченная задолженность по арендной плате
A112: за пользованием Имуществом и задолженность по уплате неустоек (штрафов, пени) по договору имущественного найма.
A113: в размере: | C113: ='Акт расч'!P49 -> -3000
A114: В связи с грубым нарушением обязательств по несвоевременной арендной плате за пользованием Имуществом, с грубым
A115: нарушением обязательств по невозврату арендованного Имущества.
A116: В отношении Вас инициировано официальное разбирательство:
A117: 1. Уже подготовленно «дело» (подборка документов) о взыскании с Вас задолженности в принудительном порядке через суд. В
A118: результате чего сумма, подлежащая к взысканию, значительно увеличится на сумму расходов государственной пошлины,
A119: исполнительного сбора, оплату юридических услуг представителей и других судебных издержек.
A120: 2. Одновременно с иском в суд подается ходатайство о применении мер по обеспечении иска.
A121: Меры по обеспечению иска:
A122: - наложение ареста на движимое имущество (включая автотранспорт).
A123: - наложение ареста на недвижимое имущество.
A124: - денежные средства, принадлежащие ответчику и находящиеся у него или у других лиц.
A125: - установление ограничения на Ваш выезд за пределы Кыргызской Республики.
... A148: Во избежание негативных последствий, указанных выше, Вам необходимо СРОЧНО!!! связаться с
A149: сотрудниками Пункта проката по телефону | G149: =Дог.!M7 -> +996 (552) 727 607 | I149: оплатить задолженность
A150: и вернуть Имущество в пятидневный срок.
B154: Дата: | C154: =F111 -> 46031 | G154: =G88 -> З. М.
J155: (Подпись)

Sheet Треб2
M1: 1
H2: =Дог.!A140 -> З. М.
J3: Контактный телефон
J4: =Дог.!M7 -> +996 (552) 727 607
J5: E-mail: alex.zin4@yandex.ru | O5: Оборудование вернули но не оплатили
A9: УВЕДОМЛЕНИЕ АРЕНДАТОРУ
D11: Уважаемый (-ая) | F11: =Дог.!$A$18 -> ХХХХ ХХХХ ХХХХ | L11: =Дог.!A23 -> ХХХХХ | M11: г.р.
A13: Согласно договору аренды оборудования за № | G13: =Дог.!J10 -> 9 | H13: =Дог.!K10 -> 1 | I13: =Дог.!L10 -> 2026 | J13: =Дог.!M10 -> 46031.872 | K13: от | L13: ='Пр №1'!J21 -> 46031
A14: Вы взяли во временное пользование Имущество и обязались оплатить арендную плату за пользование Имуществом в сроки
A15: указанные в АКТЕ РАССЧЕТА АРЕНДНОЙ ПЛАТЫ. Вы обязались оплатить задолженность не позднее 5 рабочих дней с момента
A16: подписания акта. Также вы подписали ОБЯЗАТЕЛЬСТВО по которому вы обязались погасить задолженность в срок до
A17: ='Акт расч'!N46 -> 46032
A18: Вы не оплатили стоимость арендной платы в оговоренный срок за пользование Имуществом.
A20: =H2 -> З. М. | C20: уведомляет что на | F20: ='Пр №1'!J21 -> 46031 | G20: у Вас имеется задолженность по арендной плате за пользование
A21: Имуществом в размере: | D21: ='Акт расч'!P49 -> -3000
A23: Прошу Вас до | C23: =A17+1 -> 46033 | E23: произвести оплату вашей задолженности.
A25: А также напоминаю Вам, что заключённый между нами договор имущественного найма содержит следующие пункты:
A26: 3.4. Арендатор (наниматель) обязан своевременно вносить плату за пользованием имуществом. (в соответствии со ст. 551 ГК.К.Р.)
A27: 3.5. При возврате Имущества, Арендатор обязан оплатить арендную плату за пользование Имуществом, не позднее 5 (пяти)
A28: рабочих дней с момента возврата Имущества Арендодателю.
A29: 3.6. В случае просрочки арендного платежа в установленный договором срок (5 (пять) рабочих дней), Арендатор оплачивает
A30: неустойку, в размере 1 (один) % от стоимости оборудования, за каждые сутки просрочки (стоимость оборудования указана
A31: в акте приема передачи)
A32: При подписании ОБЯЗАТЕЛЬСТВА Вас уведомили о том что, в случае просрочки выплат по обязательству, будет начисляться
A33: неустойка в соответствии со ст.320 ГК.КР., в размере 1 (один) % от оставшейся суммы общего долга за каждый день просрочки, от
A34: суммы основного долга. В рамках исполнения обязательства в случае просрочки, в первую очередь погашается неустойка.
A35: Также предупреждены, что в случае неуплаты Вами долга, дело о взыскании задолженности со всеми штрафными начислениями,
A36: будет передано в суд по месту нахождения кредитора г. Бишкек Свердловский районный суд (по адресу ул. Ибраимова д. № 64)
... A40: Ввиду вышеизложенного Вам необходимо произвести оплату образовавшейся задолженности.
B45: Дата: | C45: =F20 -> 46031 | G45: =H2 -> З. М.
J46: (Подпись)
M50: 2
H51: =H2 -> З. М.
J52: Контактный телефон
J53: =J4 -> +996 (552) 727 607
J54: E-mail: alex.zin4@yandex.ru | O54: =O5 -> Оборудование вернули но не оплатили
A58: ПРЕТЕНЗИЯ О ЗАДОЛЖЕННОСТИ
D60: Уважаемый (-ая) | F60: =Дог.!$A$18 -> ХХХХ ХХХХ ХХХХ | L60: =L11 -> ХХХХХ | M60: г.р.
A62: Согласно договору аренды оборудования за № | G62: =G13 -> 9 | H62: =H13 -> 1 | I62: =I13 -> 2026 | J62: =J13 -> 46031.872 | K62: от | L62: =L13 -> 46031
A63: Вы взяли во временное пользование Имущество и обязались оплатить арендную плату за пользование Имуществом в сроки
A64: указанные в АКТЕ РАССЧЕТА АРЕНДНОЙ ПЛАТЫ. Вы обязались оплатить задолженность не позднее 5 рабочих дней с момента
A65: подписания акта. Также вы подписали ОБЯЗАТЕЛЬСТВО по которому вы обязались погасить задолженность в срок до:
A66: =A17 -> 46032
A67: Вы не оплатили стоимость арендной платы в оговоренный срок за пользование Имуществом, не оплатили задолженность по
A68: просрочке арендного платежа и не оплатили задолженность по ОБЯЗАТЕЛЬСТВУ.
A69: =H51 -> З. М. | C69: уведомляет что на | F69: =F20 -> 46031 | G69: у Вас имеется задолженность по арендной плате за использование
A70: Имущества плюс неустойка, согласно пункту 3.6. Договора аренды оборудования Неустойка в размере 1 (один) % от стоимости
A71: оборудования, за каждые сутки просрочки. А также неустойка по ОБЯЗАТЕЛЬСТВУ в соответствии со ст.320 ГК.КР., 1 (один) % от
A72: оставшейся суммы долга за каждый день просрочки.
C73: Итого к оплате : | E73: ='Акт расч'!P49 -> -3000
A75: Требую до | C75: =F69+1 -> 46032 | E75: произвести оплату вашей задолженности и неустоек.
A77: А также напоминаю Вам, что заключённый между нами договор имущественного найма содержит следующие пункты:
A78: 7.3. При подписании данного договора Арендатор дает согласие на хранение и обработку, своих персональных данных,
A79: получение информации, носящий рекламный характер, а также на публикацию ФИО, даты рождения, фотографий в сети
A80: Интернет и в черных списках на сайтах не надежных арендаторов, в случае возникновения долговых обязательств перед
A81: Арендодателем.
A82: В случае неуплаты до указанного срока вышеуказанной денежной суммы в отношении Вас будут реализованы следующие
A83: действия:
A84: Согласно пункту 7.3. Договора аренды оборудования, Вы будете добавлены в общий черный список недобросовестных
A85: арендаторов по всему СНГ, а также Ваши данные будут размещены в аналогичных списках в социальных сетях в всемирной
A86: сети Интернет ("Одноклассники", "Фейсбук", "Инстаграм", "В контакте" и т. д.). Данные списки являются общедоступными,
A87: и любой человек вбивший Ваши данные в интернете сразу получит всю имеющуюся информацию о Вас, находящуюся
A88: на этих интернет ресурсах (сайтах) (Ваши фотографию, копию паспорта и т.д.)
... A91: Ввиду вышеизложенного требую от Вас незамедлительно принять решение по моей претензии!!!
B95: Дата: | C95: =F69 -> 46031 | G95: =G45 -> З. М.
J96: (Подпись)
M100: 3
H101: =H2 -> З. М.
J102: Контактный телефон
J103: =J4 -> +996 (552) 727 607
J104: E-mail: alex.zin4@yandex.ru | O104: =O54 -> Оборудование вернули но не оплатили
A108: ДОСУДЕБНАЯ ПРЕТЕНЗИЯ
D110: Уважаемый (-ая) | F110: =Дог.!$A$18 -> ХХХХ ХХХХ ХХХХ | L110: =L60 -> ХХХХХ | M110: г.р.
A112: Согласно договору аренды оборудования за № | G112: =G62 -> 9 | H112: =H62 -> 1 | I112: =I62 -> 2026 | J112: =J62 -> 46031.872 | K112: от | L112: =L62 -> 46031
A113: Вы взяли во временное пользование Имущество и обязались оплатить арендную плату за пользование Имуществом в сроки
A114: указанные в АКТЕ РАССЧЕТА АРЕНДНОЙ ПЛАТЫ. Вы обязались оплатить задолженность не позднее 5 рабочих дней с момента
A115: подписания акта. Также вы подписали ОБЯЗАТЕЛЬСТВО по которому вы обязались погасить задолженность в срок до:
A116: =A66 -> 46032
A117: Вы не оплатили стоимость арендной платы в оговоренный срок за пользование Имуществом. И не оплатили задолженность по
A118: ОБЯЗАТЕЛЬСТВУ.
A119: =H101 -> З. М. | C119: уведомляет что на | F119: =F69 -> 46031 | G119: у Вас имеется просроченная задолженность по арендной плате
A120: за пользованием Имуществом и задолженность по уплате неустоек (штрафов, пени) по договору имущественного найма.
A121: в размере: | C121: ='Акт расч'!P49 -> -3000
A122: В связи с грубым нарушением обязательств по несвоевременной арендной плате за пользованием Имуществом, с грубым
A123: нарушением оплаты неустоек по договору имущественного найма и с грубым нарушением оплаты неустоек по ОБЯЗАТЕЛЬСТВУ
A124: В отношении Вас инициировано официальное разбирательство:
A125: 1. Уже подготовленно «дело» (подборка документов) о взыскании с Вас задолженности в принудительном порядке через суд. В
A126: результате чего сумма, подлежащая к взысканию, значительно увеличится на сумму расходов государственной пошлины,
A127: исполнительного сбора, оплату юридических услуг представителей и других судебных издержек.
A128: 2. Одновременно с иском в суд подается ходатайство о применении мер по обеспечении иска.
A129: Меры по обеспечению иска:
A130: - наложение ареста на движимое имущество (включая автотранспорт).
A131: - наложение ареста на недвижимое имущество.
A132: - денежные средства, принадлежащие ответчику и находящиеся у него или у других лиц.
A133: - установление ограничения на Ваш выезд за пределы Кыргызской Республики.
... A152: Во избежание негативных последствий, указанных выше, Вам необходимо СРОЧНО!!! связаться с
A153: сотрудниками Пункта проката по телефону | G153: =Дог.!M7 -> +996 (552) 727 607 | I153: и оплатить задолженность
A154: в пятидневный срок.
B158: Дата: | C158: =F119 -> 46031 | G158: =G95 -> З. М.
J159: (Подпись)

Sheet Акт возв
A3: АКТ ВОЗВРАТА ИМУЩЕСТВА
A4: к Договору аренды оборудования
J5: № | K5: ='Пр №1'!J3 -> 9 | L5: ='Пр №1'!K3 -> 1 | M5: ='Пр №1'!L3 -> 2026 | N5: ='Пр №1'!M3 -> 46031.872 | O5: ='Акт расч'!O5 -> 1
B6: =Дог.!B13 -> г. Бишкек | I6: ='Пр №1'!I5 -> « | J6: ='Пр №1'!J5 -> 9 | K6: ='Пр №1'!K5 -> » | L6: ='Пр №1'!L5 -> Январь | N6: ='Пр №1'!N5 -> 2026 | O6: ='Пр №1'!O5 -> г.
A7: ='Акт расч'!A7:E7 -> Зинченко Михаил Александрович | G7: ='Счет '!G7:Q7 -> 22.12.2006 года рождения, паспорт: ID3219844 выдан MKK 218011 от 12.02.2023 г.
A8: ='Пр №1'!A7:Q7 -> зарегистрированный по адресу город Бишкек, улица Ялтинская 56/1, действующий на основании Свидетельства о государственной
A9: ='Пр №1'!A8:Q8 -> регистрации индивидуального предпринимателя по Свердловскому району г. Бишкек № 003-2024-169-5930 от 08.08.2024
A10: ИНН: | C10: ='Пр №1'!C9:G9 -> 22212200650516 | H10: именуемый в дальнейшем «Арендодатель», с одной стороны и
A11: ='Акт расч'!A11:H11 -> ХХХХ ХХХХ ХХХХ | I11: именуемый(-ая) в дальнейшем «Арендатор», действующий(-ая)
A12: =Дог.!A19 -> на основании паспорта: | E12: =Дог.!E19 -> ХХХ | F12: =Дог.!F19 -> № | G12: 2529296 | I12: =Дог.!I19 -> выдан | J12: ='Пр №1'!J11 -> МКК | K12: ='Пр №1'!K11 -> ХХХХ | L12: ='Пр №1'!L11 -> от | M12: ='Пр №1'!M11 -> ХХХХ | N12: =Дог.!N19 -> зарегистрированный(-ая)
A13: по адресу: | C13: ='Акт расч'!C13:G13 -> Чуйская область г. Бишкек | I13: ='Акт расч'!H13:M13 -> ул. ХХХХХ | N13: Факт. место проживания
A14: ='Акт расч'!A14:E14 -> Чуйская область г. Бишкек | H14: ='Пр №1'!H13:Q13 -> ул. ХХХХХ
A15: ПИН: | C15: ='Пр №1'!C14:F14 -> ХХХХ | G15: Адрес объекта: | K15: ='Пр №1'!K14:P14 -> 0
A16: с другой стороны, а вместе именуемые «Стороны», заключили настоящий акт к Договору
A17: аренды оборудования | E17: № | F17: =K5 -> 9 | G17: =L5 -> 1 | H17: =M5 -> 2026 | I17: =N5 -> 46031.872 | J17: =O5 -> 1 | K17: о нижеследующем:
A18: 1. Во исполнение Договора аренды оборудования | J18: № | K18: =K5 -> 9 | L18: =L5 -> 1 | M18: =M5 -> 2026 | N18: =N5 -> 46031.872 | O18: =O5 -> 1
A19: Арендатор возвращает Арендодателю следующее Имущество:
A20: № | B20: Наименование Имущества | G20: Стоимость оборудования | H20: Дата и время выдачи | J20: Дата и время возврата | K20: Кол-во оборуд. | L20: Кол суток | M20: Ед.изм. | N20: Цена в сутки | P20: Сумма сом
A21: 1 | B21: ='Пр №1'!B20 -> XXXXXXX | G21: ='Акт прием'!N21 -> 35000 | H21: ='Пр №1'!J20 -> 46031.872 | J21: ='Пр №1'!J20 -> 46031.872 | K21: ='Пр №1'!I20 -> 1 | L21: =J22-H22 -> 0 | M21: Сутки | N21: ='Пр №1'!N20 -> 1500 | P21: =K21*L21*N21 -> 0
H22: ='Акт расч'!F21 -> 46031 | J22: ='Пр №1'!J21 -> 46031
A23: 2 | B23: ='Пр №1'!B22 -> 0 | G23: ='Акт прием'!N23 -> 0 | K23: ='Пр №1'!I22 -> 0 | L23: =J24-H24 -> 0 | N23: ='Пр №1'!N22 -> 0 | P23: =K23*L23*N23 -> 0
A25: 3 | B25: ='Пр №1'!B24 -> 0 | G25: ='Акт прием'!N25 -> 0 | K25: ='Пр №1'!I24 -> 0 | L25: =J26-H26 -> 0 | N25: ='Пр №1'!N24 -> 0 | P25: =K25*L25*N25 -> 0
A27: 4 | B27: ='Пр №1'!B26 -> 0 | G27: ='Акт прием'!N24 -> 0 | K27: ='Пр №1'!I26 -> 0 | L27: =J28-H28 -> 0 | N27: ='Пр №1'!N26 -> 0 | P27: =K27*L27*N27 -> 0
A29: 5 | B29: ='Пр №1'!B28 -> 0 | G29: ='Акт прием'!N25 -> 0 | K29: ='Пр №1'!I28 -> 0 | L29: =J30-H30 -> 0 | N29: ='Пр №1'!N28 -> 0 | P29: =K29*L29*N29 -> 0
M31: ИТОГО: | P31: =SUM(P21:Q30) -> 0
A32: 2. Общая стоимость оказанных услуг составила | H32: =P31 -> 0
A33: 3. Имущество передается в полной исправности. Работоспособность Имущества проверена Арендодателем
A34: 4. Стороны по факту оказанных услуг претензий друг к другу не имеют.
A35: 5. Стороны считают условия Договора аренды оборудования выполненными и претензий друг к другу не имеют
A36: 6. Настоящий Акт составлен в 2-ух экземплярах, имеющих одинаковую юридическую силу, по одному для каждой из сторон.
A39: 8. РЕКВИЗИТЫ СТОРОН
A40: АРЕНДОДАТЕЛЬ: | J40: АРЕНДАТОР:
A41: Ф.И.О.: | B41: ='Пр №1'!B50:G50 -> Зинченко Михаил Александрович | J41: ='Счет '!J47:K47 -> Ф.И.О.: | L41: ='Пр №1'!L50:Q50 -> ХХХХ ХХХХ ХХХХ
A42: ИНН: | B42: ='Пр №1'!B51:G51 -> 22212200650516 | J42: ='Счет '!J48:K48 -> ПИН: | L42: ='Пр №1'!L51:P51 -> ХХХХ
A43: Паспорт: | C43: ='Пр №1'!C52 -> ID | D43: № | E43: ='Пр №1'!E52:G52 -> 3219844 | J43: ='Счет '!J49:K49 -> Паспорт: | L43: ='Пр №1'!L52 -> ХХХ | M43: № | N43: ='Пр №1'!N52:O52 -> ХХХХХ
A44: Выдан: | C44: ='Пр №1'!C53:G53 -> МКК 218011 от 12.02.2023 | J44: ='Счет '!J50:K50 -> Выдан: | L44: ='Пр №1'!L53 -> МКК | M44: ='Пр №1'!M53 -> ХХХХ | N44: ='Пр №1'!N53 -> от | O44: ='Пр №1'!O53 -> ХХХХ
A45: Адрес: | C45: ='Пр №1'!C54:G54 -> г. Бишкек | J45: ='Счет '!J51:K51 -> Адрес: | L45: ='Пр №1'!L54:Q54 -> Чуйская область г. Бишкек
A46: ='Пр №1'!A55:G55 -> ул. Ялтинская д. № 56 | J46: ='Пр №1'!J55:P55 -> ул. ХХХХХ
A47: Почтовый индекс: | D47: ='Пр №1'!D56:G56 -> 720051 | J47: ='Счет '!J53:L53 -> Почтовый индекс: | M47: ='Пр №1'!M56:N56 -> 0
A48: Банковские реквизиты: | J48: ='Счет '!J54:P54 -> Банковские реквизиты:
A49: ='Пр №1'!A58:G58 -> ОАО "МБАНК" ФИЛИАЛ "МБАНК ПЛАЗА" | J49: ='Пр №1'!J58:P58 -> 0
A50: р/c: | B50: ='Пр №1'!B59:G59 -> "1033220001521202" | J50: ='Счет '!J56 -> р/c: | K50: ='Пр №1'!K59:P59 -> 0
A51: БИК: | B51: ='Пр №1'!B60:G60 -> 103032 | J51: ='Счет '!J57 -> БИК: | K51: ='Пр №1'!K60:P60 -> 0
A52: ='Пр №1'!A61:G61 -> УГНС 003 Свердловского района | J52: ='Счет '!J58:P58 -> УГНС 000
A53: ='Пр №1'!A62 -> ОКПО: | B53: ='Пр №1'!B62 -> 33158934
A54: ='Счет '!A60:C60 -> З. М. | D54: ='Счет '!D60:F60 -> ________________________ | J54: ='Пр №1'!J63:L63 -> ХХХХ Х. Х. | M54: ________________________
D55: ='Счет '!D61:F61 -> (подпись) | M55: ='Счет '!M61:P61 -> 0
A56: ='Пр №1'!A65 -> « | B56: ='Пр №1'!B65 -> 9 | C56: ='Пр №1'!C65 -> » | D56: ='Пр №1'!D65:E65 -> Январь | F56: ='Пр №1'!F65 -> 2026 | G56: ='Пр №1'!G65 -> г. | J56: =A56 -> « | K56: =B56 -> 9 | L56: =C56 -> » | M56: =D56 -> Январь | O56: =F56 -> 2026 | P56: =G56 -> г.
A57: Телефон: | C57: ='Пр №1'!C66:G66 -> +996 (552) 727 607 | J57: Телефон: | L57: ='Пр №1'!L66:P66 -> ХХХХ ХХХ ХХХХХ

Sheet Акт слом
A3: АКТ ВОЗВРАТА ИМУЩЕСТВА
A4: к Договору аренды оборудования
J5: № | K5: ='Пр №1'!J3 -> 9 | L5: ='Пр №1'!K3 -> 1 | M5: ='Пр №1'!L3 -> 2026 | N5: ='Пр №1'!M3 -> 46031.872 | O5: ='Акт возв'!O5 -> 1
B6: =Дог.!B13 -> г. Бишкек | I6: ='Пр №1'!I5 -> « | J6: ='Пр №1'!J5 -> 9 | K6: ='Пр №1'!K5 -> » | L6: ='Пр №1'!L5 -> Январь | N6: ='Пр №1'!N5 -> 2026 | O6: ='Пр №1'!O5 -> г.
A7: ='Акт возв'!A7:E7 -> Зинченко Михаил Александрович | G7: ='Акт возв'!G7:Q7 -> 22.12.2006 года рождения, паспорт: ID3219844 выдан MKK 218011 от 12.02.2023 г.
A8: ='Пр №1'!A7:Q7 -> зарегистрированный по адресу город Бишкек, улица Ялтинская 56/1, действующий на основании Свидетельства о государственной
A9: ='Пр №1'!A8:Q8 -> регистрации индивидуального предпринимателя по Свердловскому району г. Бишкек № 003-2024-169-5930 от 08.08.2024
A10: ='Акт возв'!A10:G10 -> ИНН: | C10: ='Пр №1'!C9:G9 -> 22212200650516 | H10: именуемый в дальнейшем «Арендодатель», с одной стороны и
A11: =Дог.!A18 -> ХХХХ ХХХХ ХХХХ | I11: именуемый(-ая) в дальнейшем «Арендатор», действующий(-ая)
A12: =Дог.!A19 -> на основании паспорта: | E12: =Дог.!E19 -> ХХХ | F12: =Дог.!F19 -> № | G12: =Дог.!G19 -> ХХХХХ | I12: =Дог.!I19 -> выдан | J12: =Дог.!J19 -> МКК | K12: ='Пр №1'!K11 -> ХХХХ | L12: ='Пр №1'!L11 -> от | M12: ='Пр №1'!M11 -> ХХХХ | N12: =Дог.!N19 -> зарегистрированный(-ая)
A13: по адресу: | C13: ='Акт возв'!C13:G13 -> Чуйская область г. Бишкек | I13: ='Акт возв'!H13:M13 -> ул. ХХХХХ | N13: Факт. место проживания
A14: ='Акт возв'!A14:E14 -> Чуйская область г. Бишкек | H14: ='Пр №1'!H13:Q13 -> ул. ХХХХХ
A15: ПИН: | C15: ='Пр №1'!C14:F14 -> ХХХХ | G15: Адрес объекта: | K15: ='Пр №1'!K14:P14 -> 0
A16: с другой стороны, а вместе именуемые «Стороны», заключили настоящий акт к Договору
A17: аренды оборудования | E17: № | F17: =K5 -> 9 | G17: =L5 -> 1 | H17: =M5 -> 2026 | I17: =N5 -> 46031.872 | J17: =O5 -> 1 | K17: о нижеследующем:
A18: 1. Во исполнение Договора аренды оборудования | J18: № | K18: =K5 -> 9 | L18: =L5 -> 1 | M18: =M5 -> 2026 | N18: =N5 -> 46031.872 | O18: =O5 -> 1
A19: Арендатор возвращает Арендодателю следующее Имущество:
A20: № | B20: Наименование Имущества | G20: Стоимость оборудования | H20: Дата и время выдачи | J20: Дата и время возврата | K20: Кол-во оборуд. | L20: Кол суток | M20: Ед.изм. | N20: Цена в сутки | P20: Сумма сом
A21: 1 | B21: ='Акт возв'!B21:F22 -> XXXXXXX | G21: ='Акт прием'!N21 -> 35000 | H21: ='Пр №1'!J20 -> 46031.872 | J21: ='Пр №1'!J20 -> 46031.872 | K21: ='Акт возв'!K21:K22 -> 1 | L21: =J22-H22 -> 0 | M21: Сутки | N21: ='Пр №1'!N20 -> 1500 | P21: =K21*L21*N21 -> 0
H22: ='Пр №1'!J21 -> 46031 | J22: ='Пр №1'!J21 -> 46031
A23: 2 | B23: ='Акт возв'!B23:F24 -> 0 | G23: ='Акт прием'!N22 -> 0 | K23: ='Акт возв'!K23:K24 -> 0 | N23: ='Пр №1'!N22 -> 0
A25: 3 | B25: ='Акт возв'!B25:F26 -> 0 | G25: ='Акт прием'!N23 -> 0 | K25: ='Акт возв'!K25:K26 -> 0 | N25: ='Пр №1'!N24 -> 0
A27: 4 | B27: ='Акт возв'!B27:F28 -> 0 | G27: ='Акт прием'!N24 -> 0 | K27: ='Акт возв'!K27:K28 -> 0 | N27: ='Пр №1'!N26 -> 0
A29: 5 | B29: ='Акт возв'!B29:F30 -> 0 | G29: ='Акт прием'!N25 -> 0 | K29: ='Акт возв'!K29:K30 -> 0 | N29: ='Пр №1'!N28 -> 0
M31: ИТОГО: | P31: =SUM(P21:Q30) -> 0
A32: 2. Общая стоимость оказанных услуг составила | H32: =P31 -> 0
A33: 2.Следующее имущество возвращается в ненадлежащем состоянии:
A34: № | B34: Наименование Имущества | G34: Реально нанесенный ущерб имуществу | N34: Стоимость ущерба
A35: 1 | B35: =B21 -> XXXXXXX | N35: 3500
A36: 2 | B36: =B22 -> 0 | G36: =K22 -> 0
A37: 3 | B37: =B23 -> 0 | G37: =K23 -> 0
A38: 4
A39: 5 | B39: =B24 -> 0 | G39: =K24 -> 0
L40: Итого: | N40: =SUM(N35:Q39) -> 3500
A42: В этой связи согласно пункту 2.2. Договора аренды, за | I42: № | J42: =K18 -> 9 | K42: =L18 -> 1 | L42: =M18 -> 2026 | M42: =N18 -> 46031.872 | N42: =O18 -> 1 | O42: Арендодатель
A43: оценивает размер реально нанесённого ущерба в размере: | J43: =N40 -> 3500
A44: 3. Арендатор обязуется оплатить образовавшуюся задолженность в размере | J44: =J43 -> 3500
A45: 4. Настоящий Акт составлен в 2-ух экземплярах, имеющих одинаковую юридическую силу, по одному для каждой из сторон.
A48: 8. РЕКВИЗИТЫ СТОРОН
A49: АРЕНДОДАТЕЛЬ: | J49: АРЕНДАТОР:
A50: Ф.И.О.: | B50: ='Пр №1'!B50:G50 -> Зинченко Михаил Александрович | J50: ='Акт возв'!J41:K41 -> Ф.И.О.: | L50: ='Пр №1'!L50:Q50 -> ХХХХ ХХХХ ХХХХ
A51: ИНН: | B51: ='Пр №1'!B51:G51 -> 22212200650516 | J51: ='Акт возв'!J42:K42 -> ПИН: | L51: ='Пр №1'!L51:P51 -> ХХХХ
A52: Паспорт: | C52: ='Пр №1'!C52 -> ID | D52: № | E52: ='Пр №1'!E52:G52 -> 3219844 | J52: ='Акт возв'!J43:K43 -> Паспорт: | L52: ='Пр №1'!L52 -> ХХХ | M52: № | N52: ='Пр №1'!N52:O52 -> ХХХХХ
A53: Выдан: | C53: ='Пр №1'!C53:G53 -> МКК 218011 от 12.02.2023 | J53: ='Акт возв'!J44:K44 -> Выдан: | L53: ='Пр №1'!L53:O53 -> МКК
A54: Адрес: | C54: ='Пр №1'!C54:G54 -> г. Бишкек | J54: ='Акт возв'!J45:K45 -> Адрес: | L54: ='Пр №1'!L54:Q54 -> Чуйская область г. Бишкек
A55: ='Пр №1'!A55:G55 -> ул. Ялтинская д. № 56 | J55: ='Пр №1'!J55:P55 -> ул. ХХХХХ
A56: Почтовый индекс: | D56: ='Пр №1'!D56:G56 -> 720051 | J56: ='Акт возв'!J47:L47 -> Почтовый индекс: | M56: ='Пр №1'!M56:N56 -> 0
A57: Банковские реквизиты: | J57: ='Акт возв'!J48:P48 -> Банковские реквизиты:
A58: ='Пр №1'!A58:G58 -> ОАО "МБАНК" ФИЛИАЛ "МБАНК ПЛАЗА" | J58: ='Пр №1'!J58:P58 -> 0
A59: р/c: | B59: ='Пр №1'!B59:G59 -> "1033220001521202" | J59: ='Акт возв'!J50 -> р/c: | K59: ='Пр №1'!K59:P59 -> 0
A60: БИК: | B60: ='Пр №1'!B60:G60 -> 103032 | J60: ='Акт возв'!J51 -> БИК: | K60: ='Пр №1'!K60:P60 -> 0
A61: ='Пр №1'!A61:G61 -> УГНС 003 Свердловского района | J61: ='Акт возв'!J52:P52 -> УГНС 000
A62: ='Пр №1'!A62 -> ОКПО: | B62: ='Пр №1'!B62 -> 33158934
A63: ='Счет '!A60:C60 -> З. М. | D63: ='Счет '!D60:F60 -> ________________________ | J63: ='Пр №1'!J63:L63 -> ХХХХ Х. Х. | M63: ________________________
D64: ='Акт возв'!D55:F55 -> (подпись) | M64: ='Акт возв'!M55:P55 -> 0
A65: ='Пр №1'!A65 -> « | B65: ='Пр №1'!B65 -> 9 | C65: ='Пр №1'!C65 -> » | D65: ='Пр №1'!D65:E65 -> Январь | F65: ='Пр №1'!F65 -> 2026 | G65: ='Пр №1'!G65 -> г. | J65: =A65 -> « | K65: =B65 -> 9 | L65: =C65 -> » | M65: =D65 -> Январь | O65: =F65 -> 2026 | P65: =G65 -> г.
A66: Телефон: | C66: ='Пр №1'!C66:G66 -> +996 (552) 727 607 | J66: Телефон: | L66: ='Пр №1'!L66:P66 -> ХХХХ ХХХ ХХХХХ

Sheet Счет 
A4: СЧЕТ НА ОПЛАТУ
J5: № | K5: ='Пр №1'!J3 -> 9 | L5: ='Пр №1'!K3 -> 1 | M5: ='Пр №1'!L3 -> 2026 | N5: ='Пр №1'!M3 -> 46031.872 | O5: ='Акт слом'!O5 -> 1
B6: =Дог.!B13 -> г. Бишкек | I6: ='Пр №1'!I5 -> « | J6: ='Пр №1'!J5 -> 9 | K6: ='Пр №1'!K5 -> » | L6: ='Пр №1'!L5 -> Январь | N6: ='Пр №1'!N5 -> 2026 | O6: ='Пр №1'!O5 -> г.
A7: ='Акт расч'!A7:E7 -> Зинченко Михаил Александрович | G7: ='Акт расч'!G7:Q7 -> 22.12.2006 года рождения, паспорт: ID3219844 выдан MKK 218011 от 12.02.2023 г.
A8: ='Пр №1'!A7:Q7 -> зарегистрированный по адресу город Бишкек, улица Ялтинская 56/1, действующий на основании Свидетельства о государственной
A9: ='Пр №1'!A8:Q8 -> регистрации индивидуального предпринимателя по Свердловскому району г. Бишкек № 003-2024-169-5930 от 08.08.2024
A10: ИНН: | B10: ='Пр №1'!C9 -> 22212200650516 | E10: =A54 -> Банковские реквизиты: | H10: =A55 -> ОАО "МБАНК" ФИЛИАЛ "МБАНК ПЛАЗА" | P10: =A57 -> БИК: | Q10: =B57 -> 103032
A11: =A56 -> р/c: | B11: =B56 -> "1033220001521202" | G11: =A58 -> УГНС 003 Свердловского района
A13: 1. Во исполнение Договора аренды оборудования | J13: № | K13: =K5 -> 9 | L13: =L5 -> 1 | M13: =M5 -> 2026 | N13: =N5 -> 46031.872 | O13: =O5 -> 1
A14: Арендатор оплачивает арендную плату Арендодателю за пользование оборудованием:
A15: Арендатор: | C15: ='Акт расч'!A11 -> ХХХХ ХХХХ ХХХХ
A16: № | B16: Наименование оборудования | H16: Кол. Оборудования | J16: Кол. Суток | L16: Ед.изм. | N16: Цена в сутки | P16: Сумма сом
A17: 1 | B17: ='Акт расч'!B20 -> XXXXXXX | H17: ='Акт расч'!J20 -> 1 | J17: ='Акт расч'!L20 -> 0 | L17: ='Акт расч'!M20 -> Сут | N17: ='Акт расч'!N20 -> 1500 | P17: ='Акт расч'!P20 -> 0
A18: 2 | B18: ='Акт расч'!B22 -> 0 | H18: ='Акт расч'!J22 -> 0 | J18: ='Акт расч'!L22 -> 0 | L18: ='Акт расч'!M22 -> 0 | N18: ='Акт расч'!N22 -> 0 | P18: ='Акт расч'!P22 -> 0
A19: 3 | B19: ='Акт расч'!B24 -> 0 | H19: ='Акт расч'!J24 -> 0 | J19: ='Акт расч'!L24 -> 0 | L19: ='Акт расч'!M24 -> 0 | N19: ='Акт расч'!N24 -> 0 | P19: ='Акт расч'!P24 -> 0
A20: 4 | B20: ='Акт расч'!B26 -> 0 | H20: ='Акт расч'!J26 -> 0 | J20: ='Акт расч'!L26 -> 0 | L20: ='Акт расч'!M26 -> 0 | N20: ='Акт расч'!N26 -> 0 | P20: ='Акт расч'!P26 -> 0
A21: 5 | B21: ='Акт расч'!B28 -> 0 | H21: ='Акт расч'!J28 -> 0 | J21: ='Акт расч'!L28 -> 0 | L21: ='Акт расч'!M28 -> 0 | N21: ='Акт расч'!N28 -> 0 | P21: ='Акт расч'!P28 -> 0
A22: 6 | B22: ='Акт расч'!B30 -> 0 | H22: ='Акт расч'!J30 -> 0 | J22: ='Акт расч'!L30 -> 0 | L22: ='Акт расч'!M30 -> 0 | N22: ='Акт расч'!N30 -> 0 | P22: ='Акт расч'!P30 -> 0
A23: 7 | B23: ='Акт расч'!B32 -> 0 | H23: ='Акт расч'!J32 -> 0 | J23: ='Акт расч'!L32 -> 0 | L23: ='Акт расч'!M32 -> 0 | N23: ='Акт расч'!N32 -> 0 | P23: ='Акт расч'!P32 -> 0
A24: 8 | B24: ='Акт расч'!B34 -> 0 | H24: ='Акт расч'!J34 -> 0 | J24: ='Акт расч'!L34 -> 0 | L24: ='Акт расч'!M34 -> 0 | N24: ='Акт расч'!N34 -> 0 | P24: ='Акт расч'!P34 -> 0
A25: 9 | B25: ='Акт расч'!B36 -> 0 | H25: ='Акт расч'!J36 -> 0 | J25: ='Акт расч'!L36 -> 0 | L25: ='Акт расч'!M36 -> 0 | N25: ='Акт расч'!N36 -> 0 | P25: ='Акт расч'!P36 -> 0
A26: 10 | B26: ='Акт расч'!B38 -> 0 | H26: ='Акт расч'!J38 -> 0 | J26: ='Акт расч'!L38 -> 0 | L26: ='Акт расч'!M38 -> 0 | N26: ='Акт расч'!N38 -> 0 | P26: ='Акт расч'!P38 -> 0
A27: 11
A28: 12
A29: 13
A30: 14
A31: 15
A32: 16 | N32: Всего: | P32: =SUM(P17:Q31) -> 0
A33: 17
A34: 18
A35: 19
A36: 20
A37: 21
A38: 22
A39: 23 | B39: Итого к оплате: | P39: =P32 -> 0
A41: К оплате: | C41: =[1]!ЧислоПрописьюВалюта(P39,2) -> #NAME?
A45: 8. РЕКВИЗИТЫ СТОРОН
A46: АРЕНДОДАТЕЛЬ: | J46: АРЕНДАТОР:
A47: Ф.И.О.: | B47: ='Пр №1'!B50:G50 -> Зинченко Михаил Александрович | J47: ='Акт расч'!J60:K60 -> Ф.И.О.: | L47: ='Пр №1'!L50:Q50 -> ХХХХ ХХХХ ХХХХ
A48: ИНН: | B48: ='Пр №1'!B51:G51 -> 22212200650516 | J48: ='Акт расч'!J61:K61 -> ПИН: | L48: ='Пр №1'!L51:P51 -> ХХХХ
A49: Паспорт: | C49: ='Пр №1'!C52 -> ID | D49: № | E49: ='Пр №1'!E52:G52 -> 3219844 | J49: ='Акт расч'!J62:K62 -> Паспорт: | L49: ='Пр №1'!L52 -> ХХХ | M49: № | N49: ='Пр №1'!N52:O52 -> ХХХХХ
A50: Выдан: | C50: ='Пр №1'!C53:G53 -> МКК 218011 от 12.02.2023 | J50: ='Акт расч'!J63:K63 -> Выдан: | L50: ='Пр №1'!L53 -> МКК | M50: ='Пр №1'!M53 -> ХХХХ | O50: ='Пр №1'!N53 -> от | P50: ='Пр №1'!O53 -> ХХХХ
A51: Адрес: | C51: ='Пр №1'!C54:G54 -> г. Бишкек | J51: ='Акт расч'!J64:K64 -> Адрес: | L51: ='Пр №1'!L54:Q54 -> Чуйская область г. Бишкек
A52: ='Пр №1'!A55:G55 -> ул. Ялтинская д. № 56 | J52: ='Пр №1'!J55:P55 -> ул. ХХХХХ
A53: Почтовый индекс: | D53: ='Пр №1'!D56:G56 -> 720051 | J53: ='Акт расч'!J66:L66 -> Почтовый индекс: | M53: ='Пр №1'!M56:N56 -> 0
A54: Банковские реквизиты: | J54: ='Акт расч'!J67:P67 -> Банковские реквизиты:
A55: ='Пр №1'!A58:G58 -> ОАО "МБАНК" ФИЛИАЛ "МБАНК ПЛАЗА" | J55: ='Пр №1'!J58:P58 -> 0
A56: р/c: | B56: ='Пр №1'!B59:G59 -> "1033220001521202" | J56: ='Акт расч'!J69 -> р/c: | K56: ='Пр №1'!K59:P59 -> 0
A57: БИК: | B57: ='Пр №1'!B60:G60 -> 103032 | J57: ='Акт расч'!J70 -> БИК: | K57: ='Пр №1'!K60:P60 -> 0
A58: ='Пр №1'!A61:G61 -> УГНС 003 Свердловского района | J58: ='Акт расч'!J71:P71 -> УГНС 000
A59: ='Пр №1'!A62 -> ОКПО: | B59: ='Пр №1'!B62 -> 33158934
A60: ='Акт расч'!A73:C73 -> З. М. | D60: ='Акт расч'!D73:F73 -> ________________________ | J60: ='Пр №1'!J63:L63 -> ХХХХ Х. Х. | M60: ________________________
D61: ='Акт расч'!D74:F74 -> (подпись) | M61: ='Акт расч'!M74:P74 -> 0
A62: ='Пр №1'!A65 -> « | B62: ='Пр №1'!B65 -> 9 | C62: ='Пр №1'!C65 -> » | D62: ='Пр №1'!D65:E65 -> Январь | F62: ='Пр №1'!F65 -> 2026 | G62: ='Пр №1'!G65 -> г. | J62: =A62 -> « | K62: =B62 -> 9 | L62: =C62 -> » | M62: =D62 -> Январь | O62: =F62 -> 2026 | P62: =G62 -> г.
A63: Телефон: | C63: ='Пр №1'!C66:G66 -> +996 (552) 727 607 | J63: Телефон: | L63: ='Пр №1'!L66:P66 -> ХХХХ ХХХ ХХХХХ

Sheet Фактура
A4: СЧЕТ ФАКТУРА
J5: № | K5: ='Пр №1'!J3 -> 9 | L5: ='Пр №1'!K3 -> 1 | M5: ='Пр №1'!L3 -> 2026 | N5: ='Пр №1'!M3 -> 46031.872 | O5: 1
B6: =Дог.!B13 -> г. Бишкек | I6: ='Пр №1'!I5 -> « | J6: ='Пр №1'!J5 -> 9 | K6: ='Пр №1'!K5 -> » | L6: ='Пр №1'!L5 -> Январь | N6: ='Пр №1'!N5 -> 2026 | O6: ='Пр №1'!O5 -> г.
A7: ='Акт расч'!A7:E7 -> Зинченко Михаил Александрович | G7: ='Акт расч'!G7:Q7 -> 22.12.2006 года рождения, паспорт: ID3219844 выдан MKK 218011 от 12.02.2023 г.
A8: ='Пр №1'!A7:Q7 -> зарегистрированный по адресу город Бишкек, улица Ялтинская 56/1, действующий на основании Свидетельства о государственной
A9: ='Пр №1'!A8:Q8 -> регистрации индивидуального предпринимателя по Свердловскому району г. Бишкек № 003-2024-169-5930 от 08.08.2024
A10: ИНН: | B10: ='Пр №1'!C9 -> 22212200650516 | F10: =A54 -> Банковские реквизиты: | I10: =A55 -> ОАО "МБАНК" ФИЛИАЛ "МБАНК ПЛАЗА"
A11: =A56 -> р/c: | B11: =B56 -> "1033220001521202" | G11: =A58 -> УГНС 003 Свердловского района | L11: ='Пр №1'!A60 -> БИК: | N11: ='Пр №1'!B60 -> 103032
A13: 1. Во исполнение Договора аренды оборудования | J13: № | K13: =K5 -> 9 | L13: =L5 -> 1 | M13: =M5 -> 2026 | N13: =N5 -> 46031.872 | O13: 1
A14: Арендатор оплатил арендную плату Арендодателю за пользование оборудованием:
A15: Арендатор: | C15: ='Акт расч'!A11 -> ХХХХ ХХХХ ХХХХ
A16: № | B16: Наименование оборудования | H16: Кол. Оборудования | J16: Кол. Суток | L16: Ед.изм. | N16: Цена в сутки | P16: Сумма сом
A17: 1 | B17: ='Счет '!B17 -> XXXXXXX | H17: ='Счет '!H17:I17 -> 1 | J17: ='Счет '!J17:K17 -> 0 | L17: ='Счет '!L17:M17 -> Сут | N17: ='Счет '!N17:O17 -> 1500 | P17: ='Счет '!P17:Q17 -> 0
A18: 2 | B18: ='Счет '!B18 -> 0 | H18: ='Счет '!H18:I18 -> 0 | J18: ='Счет '!J18:K18 -> 0 | L18: ='Счет '!L18:M18 -> 0 | N18: ='Счет '!N18:O18 -> 0 | P18: ='Счет '!P18:Q18 -> 0
A19: 3 | B19: ='Счет '!B19 -> 0 | H19: ='Счет '!H19:I19 -> 0 | J19: ='Счет '!J19:K19 -> 0 | L19: ='Счет '!L19:M19 -> 0 | N19: ='Счет '!N19:O19 -> 0 | P19: ='Счет '!P19:Q19 -> 0
A20: 4 | B20: ='Счет '!B20 -> 0 | H20: ='Счет '!H20:I20 -> 0 | J20: ='Счет '!J20:K20 -> 0 | L20: ='Счет '!L20:M20 -> 0 | N20: ='Счет '!N20:O20 -> 0 | P20: ='Счет '!P20:Q20 -> 0
A21: 5 | B21: ='Счет '!B21 -> 0 | H21: ='Счет '!H21:I21 -> 0 | J21: ='Счет '!J21:K21 -> 0 | L21: ='Счет '!L21:M21 -> 0 | N21: ='Счет '!N21:O21 -> 0 | P21: ='Счет '!P21:Q21 -> 0
A22: 6 | B22: ='Счет '!B22 -> 0 | H22: ='Счет '!H22:I22 -> 0 | J22: ='Счет '!J22:K22 -> 0 | L22: ='Счет '!L22:M22 -> 0 | N22: ='Счет '!N22:O22 -> 0 | P22: ='Счет '!P22:Q22 -> 0
A23: 7 | B23: ='Счет '!B23 -> 0 | H23: ='Счет '!H23:I23 -> 0 | J23: ='Счет '!J23:K23 -> 0 | L23: ='Счет '!L23:M23 -> 0 | N23: ='Счет '!N23:O23 -> 0 | P23: ='Счет '!P23:Q23 -> 0
A24: 8 | B24: ='Счет '!B24 -> 0 | H24: ='Счет '!H24:I24 -> 0 | J24: ='Счет '!J24:K24 -> 0 | L24: ='Счет '!L24:M24 -> 0 | N24: ='Счет '!N24:O24 -> 0 | P24: ='Счет '!P24:Q24 -> 0
A25: 9 | B25: ='Счет '!B25 -> 0 | H25: ='Счет '!H25:I25 -> 0 | J25: ='Счет '!J25:K25 -> 0 | L25: ='Счет '!L25:M25 -> 0 | N25: ='Счет '!N25:O25 -> 0 | P25: ='Счет '!P25:Q25 -> 0
A26: 10 | B26: ='Счет '!B26 -> 0 | H26: ='Счет '!H26:I26 -> 0 | J26: ='Счет '!J26:K26 -> 0 | L26: ='Счет '!L26:M26 -> 0 | N26: ='Счет '!N26:O26 -> 0 | P26: ='Счет '!P26:Q26 -> 0
A27: 11 | B27: ='Счет '!B27 -> 0 | H27: ='Счет '!H27:I27 -> 0 | J27: ='Счет '!J27:K27 -> 0 | L27: ='Счет '!L27:M27 -> 0 | N27: ='Счет '!N27:O27 -> 0 | P27: ='Счет '!P27:Q27 -> 0
A28: 12 | B28: ='Счет '!B28 -> 0 | H28: ='Счет '!H28:I28 -> 0 | J28: ='Счет '!J28:K28 -> 0 | L28: ='Счет '!L28:M28 -> 0 | N28: ='Счет '!N28:O28 -> 0 | P28: ='Счет '!P28:Q28 -> 0
... A31: 15 | B31: ='Счет '!B31 -> 0 | H31: ='Счет '!H31:I31 -> 0 | J31: ='Счет '!J31:K31 -> 0 | L31: ='Счет '!L31:M31 -> 0 | N31: ='Счет '!N31:O31 -> 0 | P31: ='Счет '!P31:Q31 -> 0
A32: 16 | N32: Всего: | P32: =SUM(P17:Q31) -> 0
A33: 17
A34: 18
A35: 19
A36: 20
A37: 21
A38: 22
A39: 23 | B39: Итого к оплате: | P39: =P32 -> 0
A41: К оплате: | C41: =[1]!ЧислоПрописьюВалюта(P39,2) -> #NAME?
A45: 8. РЕКВИЗИТЫ СТОРОН
A46: АРЕНДОДАТЕЛЬ: | J46: АРЕНДАТОР:
A47: Ф.И.О.: | B47: ='Пр №1'!B50:G50 -> Зинченко Михаил Александрович | J47: ='Акт расч'!J60:K60 -> Ф.И.О.: | L47: ='Пр №1'!L50:Q50 -> ХХХХ ХХХХ ХХХХ
A48: ИНН: | B48: ='Пр №1'!B51:G51 -> 22212200650516 | J48: ='Акт расч'!J61:K61 -> ПИН: | L48: ='Пр №1'!L51:P51 -> ХХХХ
A49: Паспорт: | C49: ='Пр №1'!C52 -> ID | D49: № | E49: ='Пр №1'!E52:G52 -> 3219844 | J49: ='Акт расч'!J62:K62 -> Паспорт: | L49: ='Пр №1'!L52 -> ХХХ | M49: № | N49: ='Пр №1'!N52:O52 -> ХХХХХ
A50: Выдан: | C50: ='Пр №1'!C53:G53 -> МКК 218011 от 12.02.2023 | J50: ='Акт расч'!J63:K63 -> Выдан: | L50: ='Пр №1'!L53 -> МКК | M50: ='Пр №1'!M53 -> ХХХХ | O50: ='Пр №1'!N53 -> от | P50: ='Пр №1'!O53 -> ХХХХ
A51: Адрес: | C51: ='Пр №1'!C54:G54 -> г. Бишкек | J51: ='Акт расч'!J64:K64 -> Адрес: | L51: ='Пр №1'!L54:Q54 -> Чуйская область г. Бишкек
A52: ='Пр №1'!A55:G55 -> ул. Ялтинская д. № 56 | J52: ='Пр №1'!J55:P55 -> ул. ХХХХХ
A53: Почтовый индекс: | D53: ='Пр №1'!D56:G56 -> 720051 | J53: ='Акт расч'!J66:L66 -> Почтовый индекс: | M53: ='Пр №1'!M56:N56 -> 0
A54: Банковские реквизиты: | J54: ='Акт расч'!J67:P67 -> Банковские реквизиты:
A55: ='Пр №1'!A58:G58 -> ОАО "МБАНК" ФИЛИАЛ "МБАНК ПЛАЗА" | J55: ='Пр №1'!J58:P58 -> 0
A56: р/c: | B56: ='Пр №1'!B59:G59 -> "1033220001521202" | J56: ='Акт расч'!J69 -> р/c: | K56: ='Пр №1'!K59:P59 -> 0
A57: БИК: | B57: ='Пр №1'!B60:G60 -> 103032 | J57: ='Акт расч'!J70 -> БИК: | K57: ='Пр №1'!K60:P60 -> 0
A58: ='Пр №1'!A61:G61 -> УГНС 003 Свердловского района | J58: ='Акт расч'!J71:P71 -> УГНС 000
A59: ='Пр №1'!A62 -> ОКПО: | B59: ='Пр №1'!B62 -> 33158934
A60: ='Акт расч'!A73:C73 -> З. М. | D60: ='Акт расч'!D73:F73 -> ________________________ | J60: ='Пр №1'!J63:L63 -> ХХХХ Х. Х. | M60: ________________________
D61: ='Акт расч'!D74:F74 -> (подпись) | M61: ='Акт расч'!M74:P74 -> 0
A62: ='Пр №1'!A65 -> « | B62: ='Пр №1'!B65 -> 9 | C62: ='Пр №1'!C65 -> » | D62: ='Пр №1'!D65:E65 -> Январь | F62: ='Пр №1'!F65 -> 2026 | G62: ='Пр №1'!G65 -> г. | J62: =A62 -> « | K62: =B62 -> 9 | L62: =C62 -> » | M62: =D62 -> Январь | O62: =F62 -> 2026 | P62: =G62 -> г.
A63: Телефон: | C63: ='Пр №1'!C66:G66 -> +996 (552) 727 607 | J63: Телефон: | L63: ='Пр №1'!L66:P66 -> ХХХХ ХХХ ХХХХХ

Sheet ПКО
AP1: Унифицированная форма № КО-1 | BP1: =A8 -> Зинченко Михаил Александрович
W2: =РКО!AV2 -> Утверждена постановлением нацкомитета Кыргызской республики от 07.04.2003 №4 | BP2: =A9 -> организация
BP3: Народная аренда строительного инструмента
BP4: структурное подразделение
AZ6: Код | BP6: КВИТАНЦИЯ
AX7: Форма по ГКУД | AZ7: 0310002
A8: =Дог.!A14 -> Зинченко Михаил Александрович | AX8: по ОКПО | AZ8: 32282661
A9: организация
A10: Народная аренда строительного инструмента | BN10: к приходному кассовому ордеру № | CG10: =AJ15 -> 9 | CJ10: =AN15 -> 1 | CL10: =AQ15 -> 2026 | CP10: =AU15 -> 46031.872 | CT10: =AZ15 -> 1
A11: структурное подразделение
BP12: от « | BS12: ='Акт слом'!J6 -> 9 | BU12: » | BV12: ='Акт слом'!L6 -> Январь | CG12: ='Акт слом'!N6 -> 2026 | CK12: г.
AJ13: Номер документа | BB13: Дата
A14: ПРИХОДНЫЙ КАССОВЫЙ ОРДЕР | BB14: составления | BP14: Принято от | BX14: =TRIM(SUBSTITUTE(LEFT(I23&" ",SEARCH(" ",I23&" ")+1)&"."& MID(I23&" ",SEARCH(" ",I23&" ",SEARCH(" ",I23&" ")+1),2)&"."," .",)) -> ХХХХ Х. Х.
AJ15: =Фактура!K5 -> 9 | AN15: =Фактура!L5 -> 1 | AQ15: =Фактура!M5 -> 2026 | AU15: =Фактура!N5 -> 46031.872 | AZ15: =Фактура!O5 -> 1 | BB15: ='Пр №1'!J21 -> 46031
BP16: Основание: | BW16: =I25 -> Обеспечительный платеж
A17: Дебет | G17: Кредит | AM17: Сумма, | AW17: Код | BP17: =AI25 -> Аренда строительного оборудования
L18: код | U18: корреспон- | AD18: код | AM18: сом. тыйын. | AW18: целевого | BP18: =A26 -> XXXXXXX
L19: структурного | U19: дирующий | AD19: аналитичес- | AM19: =BU21 -> 3000 | AW19: назначения
L20: подразделения | U20: счет, субсчет | AD20: кого учета
L21: 1 | U21: 1234587 | AD21: 6598 | AM21: ='Акт расч'!P43 -> 0 | AW21: 200 | BP21: Сумма | BU21: ='Пр №1'!P30 -> 3000 | CM21: 00 | CO21: тыйын
BU22: цифрами
A23: Принято от | I23: =Дог.!A18 -> ХХХХ ХХХХ ХХХХ | BN23: =[1]!ЧислоПрописьюВалюта(BU21,2) -> #NAME?
A25: Основание: | I25: Обеспечительный платеж | AI25: Аренда строительного оборудования
A26: ='Пр №1'!B20 -> XXXXXXX | BN26: прописью
A27: Сумма | F27: =BN23 -> #NAME? | BP27: В том числе
F28: прописью
BP29: « | BQ29: =BS12 -> 9 | BS29: » | BT29: =BV12 -> Январь | CE29: =CG12 -> 2026 | CI29: г.
A30: В том числе
A31: Приложение | BN31: М. П. (штампа)
A33: Главный бухгалтер | Z33: =Дог.!A67 -> З. М. | BN33: Главный бухгалтер | CK33: =Z33 -> З. М.
N34: (подпись) | Z34: (расшифровка подписи) | CB34: (подпись) | CK34: (расшифровка подписи)
A36: Получил кассир | Z36: Купрей А. А. | BP36: Кассир | CG36: =Z36 -> Купрей А. А.
N37: (подпись) | Z37: (расшифровка подписи) | BU37: (подпись) | CG37: (расшифровка подписи)

Sheet РКО
BM1: Унифицированная форма № КО-2
AV2: Утверждена постановлением нацкомитета Кыргызской республики от 07.04.2003 №4
CT4: Код
CQ5: Форма по ОКУД | CT5: 0310002
A6: =ПКО!A8 -> Зинченко Михаил Александрович | CQ6: по ОКПО | CT6: =ПКО!AZ8 -> 32282661
A7: (организация)
A8: =ПКО!A10 -> Народная аренда строительного инструмента
A9: (структурное подразделение)
CC10: Номер документа | CT10: Дата составления
BR11: РАСХОДНЫЙ КАССОВЫЙ ОРДЕР | BU11: =ПКО!AJ15 -> 9 | BZ11: =ПКО!AN15 -> 1 | CD11: =ПКО!AQ15 -> 2026 | CJ11: =ПКО!AU15 -> 46031.872 | CQ11: =ПКО!AZ15 -> 1 | CT11: =ПКО!BB15 -> 46031
A13: Дебет | BT13: Кредит | CC13: Сумма, сом тыйын | CQ13: Код целевого назначения
H14: код структурного подразделения | AA14: корреспондирующий счет, субсчет | AV14: код аналитического учета
H15: =ПКО!L21 -> 1 | AA15: =ПКО!U21 -> 1234587 | AV15: =ПКО!AD21 -> 6598 | CC15: =ПКО!BU21 -> 3000 | CQ15: =ПКО!AW21 -> 200
A17: Выдать | H17: =ПКО!I23 -> ХХХХ ХХХХ ХХХХ
H18: (фамилия, имя, отчество)
A19: Основание: | K19: Возврат | R19: =ПКО!BW16 -> Обеспечительный платеж | AO19: =ПКО!BP17 -> Аренда строительного оборудования | BY19: =ПКО!BP18 -> XXXXXXX
A20: Сумма | G20: =ПКО!BN23 -> #NAME?
G21: (прописью)
A22: Приложение
A23: Руководитель организации | Z23: Предприниматель | BR23: ='Пр №1'!A63 -> З. М.
Z24: (должность) | AZ24: (подпись) | BR24: (расшифровка подписи)
A25: Главный бухгалтер | AK25: =ПКО!CG36 -> Купрей А. А.
S26: (подпись) | AK26: (расшифровка подписи)
A27: Получил | I27: =G20 -> #NAME?
I28: (сумма прописью)
A29: " | C29: =BU11 -> 9 | G29: " | J29: =Дог.!L13 -> Январь | AC29: =CD11 -> 2026 | AJ29: г. | BA29: Подпись
A30: По | D30: паспорту | R30: =Дог.!E19 -> ХХХ | V30: =Дог.!F19 -> № | Z30: =Дог.!G19 -> ХХХХХ | AJ30: =Дог.!I19 -> выдан | AS30: =Дог.!J19 -> МКК | AY30: =Дог.!K19 -> ХХХХ | BG30: =Дог.!L19 -> от | BL30: =Дог.!M19 -> ХХХХ | BU30: =Дог.!N19 -> зарегистрированный(-ая) | CP30: =Дог.!A20 -> по адресу:
D31: (наименование, номер, дата и место выдачи документа, удостоверяющего личность получателя)
A32: =Дог.!C20 -> Чуйская область г. Бишкек | BG32: =Дог.!J20 -> ул. ХХХХХ
A34: Выдал кассир
O35: (подпись) | AG35: (расшифровка подписи)

Sheet Обоснование
A1: 1 | B1: ФИО: | C1: =Дог.!A18 -> ХХХХ ХХХХ ХХХХ
A2: 2 | B2: ТЕКСТ: | C2: Здравствуйте!!! Опубликуйте пожалуйста!!! МОШЕННИК!!!
A3: 3 | B3: Год Рождения: | C3: =Дог.!A23 -> ХХХХХ
A4: 4 | B4: Телефон: | C4: =Дог.!D7 -> ХХХХ ХХХ ХХХХХ
A5: 5 | B5: WhatsApp:
A6: 6 | B6: Адрес по прописке: | C6: =Дог.!C20 -> Чуйская область г. Бишкек | D6: =Дог.!J20 -> ул. ХХХХХ
A7: 7 | B7: Адрес проживания: | C7: =Дог.!A21 -> Чуйская область г. Бишкек | D7: =Дог.!I21 -> ул. ХХХХХ
A8: 8 | B8: Что взял: | C8: =Дог.!A12 -> XXXXXXX
A9: 9 | B9: Когда взял: | C9: ='Акт расч'!F21 -> 46031
A10: 10 | B10: Вернул\не вернул:
A11: 11 | B11: Задолженность на дату: | C11: ='Пр №1'!J21 -> 46031 | D11: ='Акт расч'!P49 -> -3000
A12: 12 | B12: Что обещал, когда обещал:
A14: 13 | B14: Дополнительные сведения:
A16: 14 | B16: Обязательство - есть\нет:
A17: 15 | B17: Профиль INSTAGRAM:
A18: 16 | B18: Профиль FACEBOOK:
A19: 17 | B19: Профиль Одноклассники:
A20: 18 | B20: Профиль VK:
A21: 19 | B21: Пункт Проката: | C21: =Дог.!L8 -> ул. Лермонтова д.№ 68
A23: Для публикациив соц. сетях хештеги
A24: # | B24: =SUBSTITUTE(C1,CHAR(32),"") -> ХХХХХХХХХХХХ | E24: =C1 -> ХХХХ ХХХХ ХХХХ
A25: # | B25: =SUBSTITUTE(E25,CHAR(32),"") -> ХХХХХ.Х. | E25: =LEFT(E24,FIND(" ",E24,1)+1)&"."&MID(E24,FIND(" ",E24,FIND(" ",E24,1)+1)+1,1)&"." -> ХХХХ Х.Х.
A26: # | B26: =SUBSTITUTE(E26,CHAR(32),"") -> ХХХХХХХХ | E26: =LEFT(E24,SEARCH(" ",E24,SEARCH(" ",E24)+1)-1) -> ХХХХ ХХХХ
A27: # | B27: =SUBSTITUTE(E27,CHAR(32),"") -> ХХХХХХХХ | E27: =MID(E26,SEARCH(" ",E26)+1,300)&" "&MID(E26,1,SEARCH(" ",E26)) -> ХХХХ ХХХХ
A28: # | B28: =SUBSTITUTE(E28,CHAR(32),"") -> ХХХХХХХХХХХХ | E28: =TRIM(RIGHT(E24,LEN(E24)-SEARCH(" ",E24))&" "&LEFT(E24,SEARCH(" ",E24)-1)) -> ХХХХ ХХХХ ХХХХ
A29: # | B29: =SUBSTITUTE(E29,CHAR(32),"") -> ХХХХХХХХ | E29: =MID(C1,SEARCH(" ",C1)+1,99) -> ХХХХ ХХХХ
A30: #
A31: #

Sheet Письма
A1: ПИСЬМО ДЛЯ РОДСТВЕННИКОВ И ДРУЗЕЙ № 1
A3: Добрый день, хотел у вас узнать знаете ли вы гражданина Кыргызской Республики
A4: =Дог.!A18 -> ХХХХ ХХХХ ХХХХ | F4: =Дог.!A23 -> ХХХХХ | H4: данный гражданин
A5: взял и не вернул строительное оборудование на сумму: | H5: ='Акт прием'!N26 -> 35000
A6: я ищу его родственников или знакомых, может что с ним случилось, может попал
A7: в аварию, телефон недоступен по WhatsApp не отвечает. Человек производил хорошее
A8: впечатление не хотелось бы думать о нем что то дурное. Но если не найду, придется
A9: объявить его в розыск.
A10: Огромная просьба если вы его знаете дайте мне знать где он что с ним
A11: Заранее огромное спасибо за внимание!!!
B13: Дата: | C13: =Дог.!P11 -> 46031
D14: Зинченко А. А.
H15: (подпись)
A19: ПИСЬМО ДЛЯ РОДСТВЕННИКОВ И ДРУЗЕЙ № 2
A20: Добрый день. Меня зовут | E20: =Дог.!A14 -> Зинченко Михаил Александрович | I20: Я занимаюсь
A21: прокатом строительного оборудования и инструмента.
A22: Заранее приношу свои извинения за беспокойство, хотел у Вас спросить - знаком ли Вам
A23: гражданин Кыргызской Республики – | F23: =Дог.!A18 -> ХХХХ ХХХХ ХХХХ
A24: =Дог.!A23 -> ХХХХХ | C24: года рождения?
A25: Дело в том, что я ищу его родственников или знакомых, в связи с тем, что он уже более
A26: недели не отвечает на телефонные звонки и сообщения в WhatsApp.
A27: =F23 -> ХХХХ ХХХХ ХХХХ | F27: всегда производил впечатление порядочного,
A28: честного и достойного человека - не хотелось бы допускать о нем каких-то негативных
A29: мыслей. Он неоднократно брал у меня в аренду оборудование и к нему ни разу не
A30: возникало никаких претензий или нареканий.
A31: Однако | C31: ='Пр №1'!J21 -> 46031 | E31: между мной и гражданином Кыргызской Республики
A32: =A27 -> ХХХХ ХХХХ ХХХХ | G32: =A24 -> ХХХХХ | H32: года рождения был
A33: заключён официальный договор аренды оборудования. Им было взято на прокат
A34: следующее оборудование:
A35: Взятое | C35: =C31 -> 46031 | E35: года строительное оборудование до сих пор не сдано.
A36: На сегодняшний день задолженность по арендной плате составляет | I36: ='Акт расч'!P49 -> -3000
A37: =[1]!ЧислоПрописьюВалюта(I36,2) -> #NAME?
A38: составлен соответствующий Акт расчета. Он брал оборудование на несколько дней, но
A39: пропал и не выходил на связь.
A40: Я сдаю строительное оборудование в прокат людям чтобы они могли произвести
A41: различные строительно- монтажные работы и тем самым помогаю им чтобы они могли
A42: зарабатывать и обеспечивать свои семьи, или произвести у себя дома ремонт не неся при
A43: этом дополнительных ощутимых затрат на приобретение дорогостоящих строительных
A44: инструментов и оборудования, которые нужны на кратковременный период проведения
A45: работ и в дальнейшем использоваться не будут.
A46: Я всегда стараюсь войти в положение своих клиентов, даю им отсрочку по оплате или
A47: даю им возможность производить оплату в рассрочку без начисления штрафных
A48: санкций, делаю дополнительные скидки. Но когда человек постоянно обещает привезти
A49: оборудование и оплатить стоимость проката, а сам и при этом пропадает и элементарно
... A53: мне информацию о нем или передать ему чтобы он связался со мной. Мой номер
A54: телефона | C54: =Дог.!M7 -> +996 (552) 727 607 | E54: Я хочу решить всё мирным путем без обращения в
A55: соответствующие инстанции и размещения в социальных сетях информации (в частности –
A56: занесение его данных в «Общереспубликанский Черный список»), которая негативно
A57: отразится его репутации. Но если он будет и дальше скрываться я буду вынужден
A58: прибегнуть к вышеизложенным мерам, а это чревато для него дополнительными
A59: немалыми расходами и подрывом его авторитета.
A60: Огромное спасибо за Ваше внимание и надеюсь на Ваше понимание!!!
A63: С уважением, Александр.

Sheet В милицию
A2: И Н Ф О Р М А Ц И Я О З А Я В И Т Е Л Е:
A4: 1 | B4: Ф.И.О. | F4: Зинченко Александр Александрович
A5: 2 | B5: Дата рождения | F5: 30492
A6: 3 | B6: Место рождения | F6: г. Бишкек
A7: 4 | B7: Гражданство | F7: Кыргызское
A8: 5 | B8: Номер, серия и дата выдачи паспорта | F8: № ID 1706490 МKK 211041 от 05.06.2020
A9: 6 | B9: Пин \ ИНН | F9: 22506198300063
A10: 7 | B10: Адрес по прописке | F10: ул. Ялтинская д 56 \1
A11: 8 | B11: Фактический адрес проживания | F11: ул. Ялтинская д 56 \1
A12: 9 | B12: № раб. телефона | F12: 0 555 147 688
A13: 10 | B13: № дом. телефона
A14: 11 | B14: № моб. телефона | F14: 0 706 147 688
A15: 12 | B15: Место работы | F15: Индивидуальный предприниматель
A16: 13 | B16: Должность | F16: Руководитель проката
A17: 14 | B17: Образование | F17: Высшее
A18: 15 | B18: Семейное положение | F18: Женат
A19: 16 | B19: Примечание (обращался ли ранее с заявлением об этом совершённом или готовящемся преступлении\проступке в другой правоохранительный орган, если да то когда и в какой орган): | F19: нет
A20: 17 | B20: Приложение (имеются вещественные доказательства. аудио-видео запись происшествия, документы и другие, относящиеся к преступлению\проступку материалы):
A21: 18 | B21: Дополнения (любые имеющиеся дополнения в части информации о заявителе):
A22: Заявление и личные данные с моих слов напечатаны (написаны) верно, мной
A23: прочитаны (написаны, напечатаны собственноручно) -нужное подчеркнуть
D25: Подпись заявителя
H26: (подпись)
A27: «____» ___________ 2019 г. | G27: «____» час. «____»мин.
A29: Заявление принял:_______________________________________________________
A30: ________________________________________________________
A31: (должность, фамилия, инициалы, подпись)
A33: Выдан талон-уведомление №_______________________________________
G37: Начальнику УВД Свердловского
G38: района города Бишкек
G39: Полковнику милиции
G40: Тагаеву А.Г.
G41: ОТ КОГО: Зинченко
G42: Александра Александровича
A46: ЗАЯВЛЕНИЕ
A47: о совершённом или готовящемся преступлении/проступке
B49: Я, | C49: Зинченко Александр Александрович | G49: прошу привлечь к уголовной
A50: ответственности | D50: =Дог.!A18 -> ХХХХ ХХХХ ХХХХ | H50: год рож. | I50: =Дог.!A23 -> ХХХХХ
A51: за то, что он | C51: ='Пр №1'!J21 -> 46031 | E51: года примерно в | G51: ='Пр №1'!J20 -> 46031.872 | H51: часов находясь в офисе
A52: по прокату строительного инструмента расположенного по адресу | I52: =Дог.!B13 -> г. Бишкек
A53: =Дог.!L8 -> ул. Лермонтова д.№ 68 | D53: где войдя в мое доверие обманным путем завладел имуществом
A54: ='Пр №1'!B20 -> XXXXXXX
A55: китайского производства стоимостью | F55: ='Акт прием'!N21 -> 35000 | H55: а также сумма за прокат
A56: инструмента на сегодняшний день составила | F56: ='Акт расч'!P49 -> -3000 | H56: Тем самым гражданин
A57: =TRIM(SUBSTITUTE(LEFT(D50&" ",SEARCH(" ",D50&" ")+1)&"."& MID(D50&" ",SEARCH(" ",D50&" ",SEARCH(" ",D50&" ")+1),2)&"."," .",)) -> ХХХХ Х. Х. | E57: причинил мне материальный ущерб на общую сумму
A58: =F55+F56 -> 32000
A64: (краткое сведения о совершенном или готовящемся преступлении, которые заявитель
A65: должен отразить выше: о времени, места и способе совершения преступления, о
A66: полученных телесных повреждениях, обращался ли в мед учреждения, когда и где
A67: и кто производил осмотр, о преступниках или подозреваемых, роль каждого из лиц
A68: совершивших преступное посягательство, о сведениях очевидцах уголовного
A69: правонарушения, о сумме материального ущерба, о вещественных доказательствах и
A70: и другие сведения, раскрывающие суть произошедшего события)
D72: Подпись заявителя
H73: (подпись)
B75: Я, | C75: Зинченко А. А., | E75: об уголовной ответственности по ст.344 УК. КР.
A76: за ведомо ложное сообщение о совершении преступления, которое предусмотрено
A77: наказание в виде лишением свободы до 3-х лет ПРЕДУПРЕЖДЕН
D79: Подпись заявителя
H80: (подпись)
G84: Начальнику УВД Свердловского
G85: района города Бишкек
G86: Полковнику милиции
G87: Тагаеву А.Г.
G88: От гражданина Зинченко
G89: Александра Александровича
G90: 25.06.1983г.р., прож.: г. Бишкек
G91: ул. Ялтинская д.56\1
G92: работаю: И.П. по прокату строй.
G93: оборудования.
G94: тел.: 0555 147 688
A99: ОБЪЯСНИТЕЛЬНАЯ
A101: По существу дела поясную о том что я проживаю по вышеуказанному адресу
A102: со своей семьей с рождения.
A103: В настоящее время я работаю руководителем пункта проката строительного
A104: оборудования который находится по адресу | F104: =I52 -> г. Бишкек | H104: =A53 -> ул. Лермонтова д.№ 68
A105: =C51 -> 46031 | C105: приблизительно в | E105: =G51 -> 46031.872 | F105: в пункт проката пришел мужчина
A106: азиатской национальности в возрасте | F106: 30 - 35 | G106: лет и начал интересоваться
A107: разнообразным строительным оборудованием, основное внимание он акцентировал
A108: на | B108: =A54 -> XXXXXXX
A109: Я объяснил ему наши условия проката, данного оборудования
A110: где он согласился с оными и мы заключили договор аренды оборудования.
A111: Согласно заключенному договору аренды гр. | G111: =A57 -> ХХХХ Х. Х.
A112: должен был вернуть оборудование через | F112: 4 | G112: сут. По прошествии срока
A113: гр. | B113: =G111 -> ХХХХ Х. Х. | E113: оборудование не привез не продлил договор аренды
A114: на новый срок. Через два три дня я пытался дозвонится до данного гражданина
A115: но все тщетно телефон не берет хотя гудки идут, по WhatsApp не отвечает
A116: пытался писать смс, через различные соц. Сети все бесполезно. А по прошествии
A117: 2 недель и вовсе отключил телефон и до сих пор он недоступен.
A123: Объяснительная напечатана собственноручно и верно
D125: Зинченко А. А.
H126: (подпись)

Sheet Фразы для Ватсапа
B1: ЛЕРМОНТОВА 68 | C1: КЫРГЫЗ ПРОКАТ | D1: ПИШПЕК ПРОКАТ
B2: *ОПОВЕЩЕНИЕ* | C2: *ОПОВЕЩЕНИЕ* | D2: *ОПОВЕЩЕНИЕ*
B3: *НАПОМИНАНИЕ* | C3: *НАПОМИНАНИЕ* | D3: *НАПОМИНАНИЕ*
B4: *Доброе время суток* | C4: *Доброе время суток* | D4: *Доброе время суток*
B5: Вас беспокоят с пункта проката строительного оборудования *LEVEL* | C5: Вас беспокоят с пункта проката строительного оборудования *КЫРГЫЗПРОКАТ* | D5: Вас беспокоят с пункта проката строительного оборудования *ПИШПЕК ПРОКАТ*
B6: По адресу: с. Лебединовка ул. Лермонтова дом № 68 | C6: По адресу: Куттубаева 26а/3 | D6: По адресу: ВОРОВСКОГО 1\3
B7: Вы брали у нас: ----- | C7: Вы брали у нас: ------ | D7: Вы брали у нас: ------
B8: Информирую Вас что депозит закончился | C8: Информирую Вас, что депозит закончился | D8: Информирую Вас, что депозит закончился
B9: У Вас образовалась задолженность: ------- | C9: У Вас образовалась задолженность: ------ | D9: У Вас образовалась задолженность:------
B10: *РАБОЧИЙ ГРАФИК* | C10: *РАБОЧИЙ ГРАФИК* | D10: *РАБОЧИЙ ГРАФИК*
B11: С понедельника по пятницу | C11: С понедельника по пятницу | D11: С понедельника по пятницу
B12: *С 8:00 до 18:00*(семь часов вечера) | C12: *С 8:00 до 18:00*(семь часов вечера) | D12: *С 8:00 до 18:00*(семь часов вечера)
... B19: каждый день | C19: каждый день | D19: каждый день
A20: ФРАЗЫ ДЛЯ WhatsApp
B21: Вежливое общение | C21: Не большой наезд | D21: Наезд
A22: 1 | B22: Сколько Вы еще планируете пользоваться оборудованием? | C22: Обещали приехать сегодня, ----, ждём Вас. | D22: Когда Вы сдадите оборудование и оплатите арендную плату?
A23: 2 | B23: Когда Вы планируете сдать оборудование? | C23: Вы обещали приехать ---- и оплатить, но не приехали? | D23: Когда Вы оплатите арендную плату?
A24: 3 | B24: Назовите, пожалуйста дату, когда Вы планируете сдать оборудование. | C24: Вы обещали приехать -----, но не приехали? | D24: Когда Вы сдадите оборудование?
A25: 4 | B25: Сколько Вы еще планируете пользоваться оборудованием | C25: Вы обещали оплатить в течении 2 часов? | D25: Ваша задолженность растёт с каждым днём!
A26: 5 | B26: Хорошо, единственное, Вам необходимо будет пополнить депозит на --- сом | C26: *Для того чтобы пользоваться оборудованием далее, необходимо пополнить депозит на ---- сом.* | D26: *ВАМ необходимо пополнить депозит.*
A27: 6 | B27: Вы можете продолжать пользоваться данным оборудованием, Единственное, Вам необходимо будет пополнять депозит, когда задолженность превысит 3000 сом. | C27: Вы подписали Обязательство и обязались оплатить до -------- года. | D27: Я так понимаю, сдавать оборудование оплачивать арендную плату Вы не собираетесь?
A28: 7 | B28: *ВАША ЗАДОЛЖЕННОСТЬ НА ------ СОСТАВЛЯЕТ ---- СОМ* | C28: Также Вы подписали Акт расчета арендной платы по которому вы обязались оплатить не позднее 5 рабочих дней, прошло уже -- дней | D28: Я так понимаю, оплачивать арендную плату Вы не собираетесь
A29: 8 | C29: Если завтра, --------, Вы не оплатите, то будет начисляться неустойка | D29: Звоню Вам, телефон не берете.
A30: 9 | C30: С сегодняшнего дня мы начинаем начислять Вам неустойку. 1% по Акту расчета + 1% по Обязательству. | D30: Дозвонится до Вас невозможно
A31: 10 | C31: *ВЫ чего ждете пока Ваша сумма вырастит для подачи иска на Вас в Суд???* | D31: Я буду вынужден занести Вас в чёрный список.
A32: 11 | C32: *Вы адекватный человек?* | D32: Мне придется занести Вас в Черный список.
A33: 12 | C33: https://arenda.lvl.kg/category/judgment/ | D33: Зачем Вы заставляете меня размещать Вас на всеобщее обозрение.
A34: 13 | D34: Я вынужден занести Вас в следующие чёрные списки INSTAGRAM FACEBOOK.
A35: 14 | D35: Вы Размещены в Черном списке.
A36: 15
A37: 16 | B37: *ВАША ЗАДОЛЖЕННОСТЬ НА ------ СОСТАВЛЯЕТ ---- СОМ* | C37: *ВАША ЗАДОЛЖЕННОСТЬ НА ------ СОСТАВЛЯЕТ ---- СОМ*
A38: 17 | B38: *Сколько Вы еще планируете пользоваться оборудованием?* | C38: *ВАМ НЕОБХОДИМО ПОПОЛНИТЬ ДЕПОЗИТ.*
A39: 18 | B39: *Когда Вы планируете сдать оборудование?* | C39: *Вы обещали приехать -----, но не приехали?
A40: 19 | B40: Назовите, пожалуйста дату, когда Вы планируете сдать оборудование.
A41: 20 | B41: ОК договорились ждем ВАС -------
A42: 21
A43: 22
A44: 23
A45: 24
A46: 25
A47: 26
A48: 27
B49: Старые должники | C49: ОБЯЗАТЕЛЬСТВО
A50: 1 | B50: *Я буду вынужден обновить Ваши данные в чёрных списках.*
A51: 2 | B51: *Я вынужден обновить Ваши Данные в следующих чёрных списках INSTAGRAM FACEBOOK.*
A52: 3 | B52: Вы вообще адекватный человек или ……..????? | C52: *НАПОМИНАНИЕ СРОК ПОГАШЕНИЯ ДО -------*
B53: Сдайте ---- оплатите задолженность ----- сом и все ??? | C53: *ВАШ ДОЛГ НА ------ СОСТАВЛЯЕТ ---- СОМ*
B54: Зачем Вы усугубляете себе же жизнь??? | C54: *ВАША ЗАДОЛЖЕННОСТЬ НА ------ СОСТАВЛЯЕТ ---- СОМ*
B55: ВЫ хотите через суд и в два раза больше???
